{"primaryContentSections":[{"kind":"declarations","declarations":[{"tokens":[{"kind":"keyword","text":"class"},{"kind":"text","text":" "},{"kind":"identifier","text":"TreeItem"}],"languages":["swift"],"platforms":["macOS"]}]}],"schemaVersion":{"major":0,"minor":3,"patch":0},"sections":[],"variants":[{"paths":["\/documentation\/godot\/treeitem"],"traits":[{"interfaceLanguage":"swift"}]}],"relationshipsSections":[{"identifiers":["doc:\/\/Godot\/documentation\/Godot\/Object"],"kind":"relationships","title":"Inherits From","type":"inheritsFrom"},{"identifiers":["doc:\/\/Godot\/documentation\/Godot\/ConvertibleFromVariant","doc:\/\/Godot\/documentation\/Godot\/ConvertibleToVariant","doc:\/\/Godot\/SQ","doc:\/\/Godot\/documentation\/Godot\/VariantConvertible"],"kind":"relationships","title":"Conforms To","type":"conformsTo"}],"identifier":{"url":"doc:\/\/Godot\/documentation\/Godot\/TreeItem","interfaceLanguage":"swift"},"topicSections":[{"title":"Instance Properties","identifiers":["doc:\/\/Godot\/documentation\/Godot\/TreeItem\/customMinimumHeight","doc:\/\/Godot\/documentation\/Godot\/TreeItem\/isCollapsed","doc:\/\/Godot\/documentation\/Godot\/TreeItem\/isFoldingDisabled","doc:\/\/Godot\/documentation\/Godot\/TreeItem\/isVisible"]},{"title":"Instance Methods","identifiers":["doc:\/\/Godot\/documentation\/Godot\/TreeItem\/addButton(column:button:id:disabled:tooltipText:)","doc:\/\/Godot\/documentation\/Godot\/TreeItem\/addChild(_:)","doc:\/\/Godot\/documentation\/Godot\/TreeItem\/autowrapMode(column:)","doc:\/\/Godot\/documentation\/Godot\/TreeItem\/button(column:buttonIndex:)","doc:\/\/Godot\/documentation\/Godot\/TreeItem\/buttonById(column:id:)","doc:\/\/Godot\/documentation\/Godot\/TreeItem\/buttonCount(column:)","doc:\/\/Godot\/documentation\/Godot\/TreeItem\/buttonId(column:buttonIndex:)","doc:\/\/Godot\/documentation\/Godot\/TreeItem\/buttonTooltipText(column:buttonIndex:)","doc:\/\/Godot\/documentation\/Godot\/TreeItem\/callRecursive(method:)","doc:\/\/Godot\/documentation\/Godot\/TreeItem\/callRecursive(method:_:)","doc:\/\/Godot\/documentation\/Godot\/TreeItem\/cellMode(column:)","doc:\/\/Godot\/documentation\/Godot\/TreeItem\/child(index:)","doc:\/\/Godot\/documentation\/Godot\/TreeItem\/childCount()","doc:\/\/Godot\/documentation\/Godot\/TreeItem\/children()","doc:\/\/Godot\/documentation\/Godot\/TreeItem\/clearCustomBgColor(column:)","doc:\/\/Godot\/documentation\/Godot\/TreeItem\/clearCustomColor(column:)","doc:\/\/Godot\/documentation\/Godot\/TreeItem\/createChild(index:)","doc:\/\/Godot\/documentation\/Godot\/TreeItem\/customBgColor(column:)","doc:\/\/Godot\/documentation\/Godot\/TreeItem\/customColor(column:)","doc:\/\/Godot\/documentation\/Godot\/TreeItem\/customFont(column:)","doc:\/\/Godot\/documentation\/Godot\/TreeItem\/customFontSize(column:)","doc:\/\/Godot\/documentation\/Godot\/TreeItem\/deselect(column:)","doc:\/\/Godot\/documentation\/Godot\/TreeItem\/eraseButton(column:buttonIndex:)","doc:\/\/Godot\/documentation\/Godot\/TreeItem\/expandRight(column:)","doc:\/\/Godot\/documentation\/Godot\/TreeItem\/firstChild()","doc:\/\/Godot\/documentation\/Godot\/TreeItem\/icon(column:)","doc:\/\/Godot\/documentation\/Godot\/TreeItem\/iconMaxWidth(column:)","doc:\/\/Godot\/documentation\/Godot\/TreeItem\/iconModulate(column:)","doc:\/\/Godot\/documentation\/Godot\/TreeItem\/iconRegion(column:)","doc:\/\/Godot\/documentation\/Godot\/TreeItem\/index()","doc:\/\/Godot\/documentation\/Godot\/TreeItem\/isAnyCollapsed(onlyVisible:)","doc:\/\/Godot\/documentation\/Godot\/TreeItem\/isButtonDisabled(column:buttonIndex:)","doc:\/\/Godot\/documentation\/Godot\/TreeItem\/isChecked(column:)","doc:\/\/Godot\/documentation\/Godot\/TreeItem\/isCustomSetAsButton(column:)","doc:\/\/Godot\/documentation\/Godot\/TreeItem\/isEditMultiline(column:)","doc:\/\/Godot\/documentation\/Godot\/TreeItem\/isEditable(column:)","doc:\/\/Godot\/documentation\/Godot\/TreeItem\/isIndeterminate(column:)","doc:\/\/Godot\/documentation\/Godot\/TreeItem\/isSelectable(column:)","doc:\/\/Godot\/documentation\/Godot\/TreeItem\/isSelected(column:)","doc:\/\/Godot\/documentation\/Godot\/TreeItem\/language(column:)","doc:\/\/Godot\/documentation\/Godot\/TreeItem\/metadata(column:)","doc:\/\/Godot\/documentation\/Godot\/TreeItem\/moveAfter(item:)","doc:\/\/Godot\/documentation\/Godot\/TreeItem\/moveBefore(item:)","doc:\/\/Godot\/documentation\/Godot\/TreeItem\/next()","doc:\/\/Godot\/documentation\/Godot\/TreeItem\/nextInTree(wrap:)","doc:\/\/Godot\/documentation\/Godot\/TreeItem\/nextVisible(wrap:)","doc:\/\/Godot\/documentation\/Godot\/TreeItem\/parent()","doc:\/\/Godot\/documentation\/Godot\/TreeItem\/prev()","doc:\/\/Godot\/documentation\/Godot\/TreeItem\/prevInTree(wrap:)","doc:\/\/Godot\/documentation\/Godot\/TreeItem\/prevVisible(wrap:)","doc:\/\/Godot\/documentation\/Godot\/TreeItem\/propagateCheck(column:emitSignal:)","doc:\/\/Godot\/documentation\/Godot\/TreeItem\/range(column:)","doc:\/\/Godot\/documentation\/Godot\/TreeItem\/rangeConfig(column:)","doc:\/\/Godot\/documentation\/Godot\/TreeItem\/removeChild(_:)","doc:\/\/Godot\/documentation\/Godot\/TreeItem\/select(column:)","doc:\/\/Godot\/documentation\/Godot\/TreeItem\/setAutowrapMode(column:autowrapMode:)","doc:\/\/Godot\/documentation\/Godot\/TreeItem\/setButton(column:buttonIndex:button:)","doc:\/\/Godot\/documentation\/Godot\/TreeItem\/setButtonColor(column:buttonIndex:color:)","doc:\/\/Godot\/documentation\/Godot\/TreeItem\/setButtonDisabled(column:buttonIndex:disabled:)","doc:\/\/Godot\/documentation\/Godot\/TreeItem\/setCellMode(column:mode:)","doc:\/\/Godot\/documentation\/Godot\/TreeItem\/setChecked(column:checked:)","doc:\/\/Godot\/documentation\/Godot\/TreeItem\/setCollapsedRecursive(enable:)","doc:\/\/Godot\/documentation\/Godot\/TreeItem\/setCustomAsButton(column:enable:)","doc:\/\/Godot\/documentation\/Godot\/TreeItem\/setCustomBgColor(column:color:justOutline:)","doc:\/\/Godot\/documentation\/Godot\/TreeItem\/setCustomColor(column:color:)","doc:\/\/Godot\/documentation\/Godot\/TreeItem\/setCustomDraw(column:object:callback:)","doc:\/\/Godot\/documentation\/Godot\/TreeItem\/setCustomFont(column:font:)","doc:\/\/Godot\/documentation\/Godot\/TreeItem\/setCustomFontSize(column:fontSize:)","doc:\/\/Godot\/documentation\/Godot\/TreeItem\/setEditMultiline(column:multiline:)","doc:\/\/Godot\/documentation\/Godot\/TreeItem\/setEditable(column:enabled:)","doc:\/\/Godot\/documentation\/Godot\/TreeItem\/setExpandRight(column:enable:)","doc:\/\/Godot\/documentation\/Godot\/TreeItem\/setIcon(column:texture:)","doc:\/\/Godot\/documentation\/Godot\/TreeItem\/setIconMaxWidth(column:width:)","doc:\/\/Godot\/documentation\/Godot\/TreeItem\/setIconModulate(column:modulate:)","doc:\/\/Godot\/documentation\/Godot\/TreeItem\/setIconRegion(column:region:)","doc:\/\/Godot\/documentation\/Godot\/TreeItem\/setIndeterminate(column:indeterminate:)","doc:\/\/Godot\/documentation\/Godot\/TreeItem\/setLanguage(column:language:)","doc:\/\/Godot\/documentation\/Godot\/TreeItem\/setMetadata(column:meta:)","doc:\/\/Godot\/documentation\/Godot\/TreeItem\/setRange(column:value:)","doc:\/\/Godot\/documentation\/Godot\/TreeItem\/setRangeConfig(column:min:max:step:expr:)","doc:\/\/Godot\/documentation\/Godot\/TreeItem\/setSelectable(column:selectable:)","doc:\/\/Godot\/documentation\/Godot\/TreeItem\/setStructuredTextBidiOverride(column:parser:)","doc:\/\/Godot\/documentation\/Godot\/TreeItem\/setStructuredTextBidiOverrideOptions(column:args:)","doc:\/\/Godot\/documentation\/Godot\/TreeItem\/setSuffix(column:text:)","doc:\/\/Godot\/documentation\/Godot\/TreeItem\/setText(column:text:)","doc:\/\/Godot\/documentation\/Godot\/TreeItem\/setTextAlignment(column:textAlignment:)","doc:\/\/Godot\/documentation\/Godot\/TreeItem\/setTextDirection(column:direction:)","doc:\/\/Godot\/documentation\/Godot\/TreeItem\/setTooltipText(column:tooltip:)","doc:\/\/Godot\/documentation\/Godot\/TreeItem\/structuredTextBidiOverride(column:)","doc:\/\/Godot\/documentation\/Godot\/TreeItem\/structuredTextBidiOverrideOptions(column:)","doc:\/\/Godot\/documentation\/Godot\/TreeItem\/suffix(column:)","doc:\/\/Godot\/documentation\/Godot\/TreeItem\/text(column:)","doc:\/\/Godot\/documentation\/Godot\/TreeItem\/textAlignment(column:)","doc:\/\/Godot\/documentation\/Godot\/TreeItem\/textDirection(column:)","doc:\/\/Godot\/documentation\/Godot\/TreeItem\/tooltipText(column:)","doc:\/\/Godot\/documentation\/Godot\/TreeItem\/tree()","doc:\/\/Godot\/documentation\/Godot\/TreeItem\/uncollapseTree()"]},{"title":"Enumerations","identifiers":["doc:\/\/Godot\/documentation\/Godot\/TreeItem\/TreeCellMode"]}],"kind":"symbol","metadata":{"fragments":[{"kind":"keyword","text":"class"},{"kind":"text","text":" "},{"kind":"identifier","text":"TreeItem"}],"title":"TreeItem","roleHeading":"Class","role":"symbol","symbolKind":"class","externalID":"s:5Godot8TreeItemC","modules":[{"name":"Godot"}],"navigatorTitle":[{"kind":"identifier","text":"TreeItem"}]},"hierarchy":{"paths":[["doc:\/\/Godot\/documentation\/Godot"]]},"references":{"doc://Godot/documentation/Godot/ConvertibleToVariant":{"role":"symbol","title":"ConvertibleToVariant","fragments":[{"kind":"keyword","text":"protocol"},{"kind":"text","text":" "},{"kind":"identifier","text":"ConvertibleToVariant"}],"abstract":[{"type":"text","text":"A type that can be converted to a variant."}],"identifier":"doc:\/\/Godot\/documentation\/Godot\/ConvertibleToVariant","kind":"symbol","type":"topic","navigatorTitle":[{"kind":"identifier","text":"ConvertibleToVariant"}],"url":"\/documentation\/godot\/convertibletovariant"},"doc://Godot/documentation/Godot/TreeItem/TreeCellMode":{"role":"symbol","title":"TreeItem.TreeCellMode","fragments":[{"kind":"keyword","text":"enum"},{"kind":"text","text":" "},{"kind":"identifier","text":"TreeCellMode"}],"abstract":[],"identifier":"doc:\/\/Godot\/documentation\/Godot\/TreeItem\/TreeCellMode","kind":"symbol","type":"topic","navigatorTitle":[{"kind":"identifier","text":"TreeCellMode"}],"url":"\/documentation\/godot\/treeitem\/treecellmode"},"doc://Godot/documentation/Godot/TreeItem/isFoldingDisabled":{"role":"symbol","title":"isFoldingDisabled","fragments":[{"kind":"keyword","text":"var"},{"kind":"text","text":" "},{"kind":"identifier","text":"isFoldingDisabled"},{"kind":"text","text":": "},{"kind":"typeIdentifier","text":"Bool","preciseIdentifier":"s:Sb"}],"abstract":[],"identifier":"doc:\/\/Godot\/documentation\/Godot\/TreeItem\/isFoldingDisabled","kind":"symbol","type":"topic","url":"\/documentation\/godot\/treeitem\/isfoldingdisabled"},"doc://Godot/documentation/Godot/TreeItem/setCustomColor(column:color:)":{"role":"symbol","title":"setCustomColor(column:color:)","fragments":[{"kind":"keyword","text":"func"},{"kind":"text","text":" "},{"kind":"identifier","text":"setCustomColor"},{"kind":"text","text":"("},{"kind":"externalParam","text":"column"},{"kind":"text","text":": "},{"kind":"typeIdentifier","text":"Int32","preciseIdentifier":"s:s5Int32V"},{"kind":"text","text":", "},{"kind":"externalParam","text":"color"},{"kind":"text","text":": Godot"},{"kind":"text","text":"."},{"kind":"typeIdentifier","text":"Color","preciseIdentifier":"s:5Godot5ColorV"},{"kind":"text","text":")"}],"abstract":[],"identifier":"doc:\/\/Godot\/documentation\/Godot\/TreeItem\/setCustomColor(column:color:)","kind":"symbol","type":"topic","url":"\/documentation\/godot\/treeitem\/setcustomcolor(column:color:)"},"doc://Godot/documentation/Godot/TreeItem/metadata(column:)":{"role":"symbol","title":"metadata(column:)","fragments":[{"kind":"keyword","text":"func"},{"kind":"text","text":" "},{"kind":"identifier","text":"metadata"},{"kind":"text","text":"("},{"kind":"externalParam","text":"column"},{"kind":"text","text":": "},{"kind":"typeIdentifier","text":"Int32","preciseIdentifier":"s:s5Int32V"},{"kind":"text","text":") -> Godot"},{"kind":"text","text":"."},{"kind":"typeIdentifier","text":"Variant","preciseIdentifier":"s:5Godot7VariantC"}],"abstract":[],"identifier":"doc:\/\/Godot\/documentation\/Godot\/TreeItem\/metadata(column:)","kind":"symbol","type":"topic","url":"\/documentation\/godot\/treeitem\/metadata(column:)"},"doc://Godot/documentation/Godot/TreeItem/setTooltipText(column:tooltip:)":{"role":"symbol","title":"setTooltipText(column:tooltip:)","fragments":[{"kind":"keyword","text":"func"},{"kind":"text","text":" "},{"kind":"identifier","text":"setTooltipText"},{"kind":"text","text":"("},{"kind":"externalParam","text":"column"},{"kind":"text","text":": "},{"kind":"typeIdentifier","text":"Int32","preciseIdentifier":"s:s5Int32V"},{"kind":"text","text":", "},{"kind":"externalParam","text":"tooltip"},{"kind":"text","text":": Godot"},{"kind":"text","text":"."},{"kind":"typeIdentifier","text":"GodotString","preciseIdentifier":"s:5Godot0A6StringV"},{"kind":"text","text":")"}],"abstract":[],"identifier":"doc:\/\/Godot\/documentation\/Godot\/TreeItem\/setTooltipText(column:tooltip:)","kind":"symbol","type":"topic","url":"\/documentation\/godot\/treeitem\/settooltiptext(column:tooltip:)"},"doc://Godot/documentation/Godot/TreeItem/customBgColor(column:)":{"role":"symbol","title":"customBgColor(column:)","fragments":[{"kind":"keyword","text":"func"},{"kind":"text","text":" "},{"kind":"identifier","text":"customBgColor"},{"kind":"text","text":"("},{"kind":"externalParam","text":"column"},{"kind":"text","text":": "},{"kind":"typeIdentifier","text":"Int32","preciseIdentifier":"s:s5Int32V"},{"kind":"text","text":") -> Godot"},{"kind":"text","text":"."},{"kind":"typeIdentifier","text":"Color","preciseIdentifier":"s:5Godot5ColorV"}],"abstract":[],"identifier":"doc:\/\/Godot\/documentation\/Godot\/TreeItem\/customBgColor(column:)","kind":"symbol","type":"topic","url":"\/documentation\/godot\/treeitem\/custombgcolor(column:)"},"doc://Godot/documentation/Godot/TreeItem/children()":{"role":"symbol","title":"children()","fragments":[{"kind":"keyword","text":"func"},{"kind":"text","text":" "},{"kind":"identifier","text":"children"},{"kind":"text","text":"() -> Godot"},{"kind":"text","text":"."},{"kind":"typeIdentifier","text":"GodotTypedArray","preciseIdentifier":"s:5Godot0A10TypedArrayV"},{"kind":"text","text":"<Godot"},{"kind":"text","text":"."},{"kind":"typeIdentifier","text":"TreeItem","preciseIdentifier":"s:5Godot8TreeItemC"},{"kind":"text","text":"?>"}],"abstract":[],"identifier":"doc:\/\/Godot\/documentation\/Godot\/TreeItem\/children()","kind":"symbol","type":"topic","url":"\/documentation\/godot\/treeitem\/children()"},"doc://Godot/documentation/Godot/TreeItem/isCustomSetAsButton(column:)":{"role":"symbol","title":"isCustomSetAsButton(column:)","fragments":[{"kind":"keyword","text":"func"},{"kind":"text","text":" "},{"kind":"identifier","text":"isCustomSetAsButton"},{"kind":"text","text":"("},{"kind":"externalParam","text":"column"},{"kind":"text","text":": "},{"kind":"typeIdentifier","text":"Int32","preciseIdentifier":"s:s5Int32V"},{"kind":"text","text":") -> "},{"kind":"typeIdentifier","text":"Bool","preciseIdentifier":"s:Sb"}],"abstract":[],"identifier":"doc:\/\/Godot\/documentation\/Godot\/TreeItem\/isCustomSetAsButton(column:)","kind":"symbol","type":"topic","url":"\/documentation\/godot\/treeitem\/iscustomsetasbutton(column:)"},"doc://Godot/documentation/Godot/TreeItem/childCount()":{"role":"symbol","title":"childCount()","fragments":[{"kind":"keyword","text":"func"},{"kind":"text","text":" "},{"kind":"identifier","text":"childCount"},{"kind":"text","text":"() -> "},{"kind":"typeIdentifier","text":"Int32","preciseIdentifier":"s:s5Int32V"}],"abstract":[],"identifier":"doc:\/\/Godot\/documentation\/Godot\/TreeItem\/childCount()","kind":"symbol","type":"topic","url":"\/documentation\/godot\/treeitem\/childcount()"},"doc://Godot/documentation/Godot/TreeItem/setCustomFontSize(column:fontSize:)":{"role":"symbol","title":"setCustomFontSize(column:fontSize:)","fragments":[{"kind":"keyword","text":"func"},{"kind":"text","text":" "},{"kind":"identifier","text":"setCustomFontSize"},{"kind":"text","text":"("},{"kind":"externalParam","text":"column"},{"kind":"text","text":": "},{"kind":"typeIdentifier","text":"Int32","preciseIdentifier":"s:s5Int32V"},{"kind":"text","text":", "},{"kind":"externalParam","text":"fontSize"},{"kind":"text","text":": "},{"kind":"typeIdentifier","text":"Int32","preciseIdentifier":"s:s5Int32V"},{"kind":"text","text":")"}],"abstract":[],"identifier":"doc:\/\/Godot\/documentation\/Godot\/TreeItem\/setCustomFontSize(column:fontSize:)","kind":"symbol","type":"topic","url":"\/documentation\/godot\/treeitem\/setcustomfontsize(column:fontsize:)"},"doc://Godot/documentation/Godot/TreeItem/setSelectable(column:selectable:)":{"role":"symbol","title":"setSelectable(column:selectable:)","fragments":[{"kind":"keyword","text":"func"},{"kind":"text","text":" "},{"kind":"identifier","text":"setSelectable"},{"kind":"text","text":"("},{"kind":"externalParam","text":"column"},{"kind":"text","text":": "},{"kind":"typeIdentifier","text":"Int32","preciseIdentifier":"s:s5Int32V"},{"kind":"text","text":", "},{"kind":"externalParam","text":"selectable"},{"kind":"text","text":": "},{"kind":"typeIdentifier","text":"Bool","preciseIdentifier":"s:Sb"},{"kind":"text","text":")"}],"abstract":[],"identifier":"doc:\/\/Godot\/documentation\/Godot\/TreeItem\/setSelectable(column:selectable:)","kind":"symbol","type":"topic","url":"\/documentation\/godot\/treeitem\/setselectable(column:selectable:)"},"doc://Godot/documentation/Godot/TreeItem/clearCustomColor(column:)":{"role":"symbol","title":"clearCustomColor(column:)","fragments":[{"kind":"keyword","text":"func"},{"kind":"text","text":" "},{"kind":"identifier","text":"clearCustomColor"},{"kind":"text","text":"("},{"kind":"externalParam","text":"column"},{"kind":"text","text":": "},{"kind":"typeIdentifier","text":"Int32","preciseIdentifier":"s:s5Int32V"},{"kind":"text","text":")"}],"abstract":[],"identifier":"doc:\/\/Godot\/documentation\/Godot\/TreeItem\/clearCustomColor(column:)","kind":"symbol","type":"topic","url":"\/documentation\/godot\/treeitem\/clearcustomcolor(column:)"},"doc://Godot/documentation/Godot/TreeItem/addButton(column:button:id:disabled:tooltipText:)":{"role":"symbol","title":"addButton(column:button:id:disabled:tooltipText:)","fragments":[{"kind":"keyword","text":"func"},{"kind":"text","text":" "},{"kind":"identifier","text":"addButton"},{"kind":"text","text":"("},{"kind":"externalParam","text":"column"},{"kind":"text","text":": "},{"kind":"typeIdentifier","text":"Int32","preciseIdentifier":"s:s5Int32V"},{"kind":"text","text":", "},{"kind":"externalParam","text":"button"},{"kind":"text","text":": Godot"},{"kind":"text","text":"."},{"kind":"typeIdentifier","text":"Texture2D","preciseIdentifier":"s:5Godot9Texture2DC"},{"kind":"text","text":"?, "},{"kind":"externalParam","text":"id"},{"kind":"text","text":": "},{"kind":"typeIdentifier","text":"Int32","preciseIdentifier":"s:s5Int32V"},{"kind":"text","text":", "},{"kind":"externalParam","text":"disabled"},{"kind":"text","text":": "},{"kind":"typeIdentifier","text":"Bool","preciseIdentifier":"s:Sb"},{"kind":"text","text":", "},{"kind":"externalParam","text":"tooltipText"},{"kind":"text","text":": Godot"},{"kind":"text","text":"."},{"kind":"typeIdentifier","text":"GodotString","preciseIdentifier":"s:5Godot0A6StringV"},{"kind":"text","text":")"}],"abstract":[],"identifier":"doc:\/\/Godot\/documentation\/Godot\/TreeItem\/addButton(column:button:id:disabled:tooltipText:)","kind":"symbol","type":"topic","url":"\/documentation\/godot\/treeitem\/addbutton(column:button:id:disabled:tooltiptext:)"},"doc://Godot/documentation/Godot/TreeItem/clearCustomBgColor(column:)":{"role":"symbol","title":"clearCustomBgColor(column:)","fragments":[{"kind":"keyword","text":"func"},{"kind":"text","text":" "},{"kind":"identifier","text":"clearCustomBgColor"},{"kind":"text","text":"("},{"kind":"externalParam","text":"column"},{"kind":"text","text":": "},{"kind":"typeIdentifier","text":"Int32","preciseIdentifier":"s:s5Int32V"},{"kind":"text","text":")"}],"abstract":[],"identifier":"doc:\/\/Godot\/documentation\/Godot\/TreeItem\/clearCustomBgColor(column:)","kind":"symbol","type":"topic","url":"\/documentation\/godot\/treeitem\/clearcustombgcolor(column:)"},"doc://Godot/documentation/Godot/TreeItem/nextInTree(wrap:)":{"role":"symbol","title":"nextInTree(wrap:)","fragments":[{"kind":"keyword","text":"func"},{"kind":"text","text":" "},{"kind":"identifier","text":"nextInTree"},{"kind":"text","text":"("},{"kind":"externalParam","text":"wrap"},{"kind":"text","text":": "},{"kind":"typeIdentifier","text":"Bool","preciseIdentifier":"s:Sb"},{"kind":"text","text":") -> Godot"},{"kind":"text","text":"."},{"kind":"typeIdentifier","text":"TreeItem","preciseIdentifier":"s:5Godot8TreeItemC"},{"kind":"text","text":"?"}],"abstract":[],"identifier":"doc:\/\/Godot\/documentation\/Godot\/TreeItem\/nextInTree(wrap:)","kind":"symbol","type":"topic","url":"\/documentation\/godot\/treeitem\/nextintree(wrap:)"},"doc://Godot/documentation/Godot/TreeItem/prev()":{"role":"symbol","title":"prev()","fragments":[{"kind":"keyword","text":"func"},{"kind":"text","text":" "},{"kind":"identifier","text":"prev"},{"kind":"text","text":"() -> Godot"},{"kind":"text","text":"."},{"kind":"typeIdentifier","text":"TreeItem","preciseIdentifier":"s:5Godot8TreeItemC"},{"kind":"text","text":"?"}],"abstract":[],"identifier":"doc:\/\/Godot\/documentation\/Godot\/TreeItem\/prev()","kind":"symbol","type":"topic","url":"\/documentation\/godot\/treeitem\/prev()"},"doc://Godot/documentation/Godot/TreeItem/customFont(column:)":{"role":"symbol","title":"customFont(column:)","fragments":[{"kind":"keyword","text":"func"},{"kind":"text","text":" "},{"kind":"identifier","text":"customFont"},{"kind":"text","text":"("},{"kind":"externalParam","text":"column"},{"kind":"text","text":": "},{"kind":"typeIdentifier","text":"Int32","preciseIdentifier":"s:s5Int32V"},{"kind":"text","text":") -> Godot"},{"kind":"text","text":"."},{"kind":"typeIdentifier","text":"Font","preciseIdentifier":"s:5Godot4FontC"},{"kind":"text","text":"?"}],"abstract":[],"identifier":"doc:\/\/Godot\/documentation\/Godot\/TreeItem\/customFont(column:)","kind":"symbol","type":"topic","url":"\/documentation\/godot\/treeitem\/customfont(column:)"},"doc://Godot/documentation/Godot/TreeItem/setIconModulate(column:modulate:)":{"role":"symbol","title":"setIconModulate(column:modulate:)","fragments":[{"kind":"keyword","text":"func"},{"kind":"text","text":" "},{"kind":"identifier","text":"setIconModulate"},{"kind":"text","text":"("},{"kind":"externalParam","text":"column"},{"kind":"text","text":": "},{"kind":"typeIdentifier","text":"Int32","preciseIdentifier":"s:s5Int32V"},{"kind":"text","text":", "},{"kind":"externalParam","text":"modulate"},{"kind":"text","text":": Godot"},{"kind":"text","text":"."},{"kind":"typeIdentifier","text":"Color","preciseIdentifier":"s:5Godot5ColorV"},{"kind":"text","text":")"}],"abstract":[],"identifier":"doc:\/\/Godot\/documentation\/Godot\/TreeItem\/setIconModulate(column:modulate:)","kind":"symbol","type":"topic","url":"\/documentation\/godot\/treeitem\/seticonmodulate(column:modulate:)"},"doc://Godot/documentation/Godot/TreeItem/isChecked(column:)":{"role":"symbol","title":"isChecked(column:)","fragments":[{"kind":"keyword","text":"func"},{"kind":"text","text":" "},{"kind":"identifier","text":"isChecked"},{"kind":"text","text":"("},{"kind":"externalParam","text":"column"},{"kind":"text","text":": "},{"kind":"typeIdentifier","text":"Int32","preciseIdentifier":"s:s5Int32V"},{"kind":"text","text":") -> "},{"kind":"typeIdentifier","text":"Bool","preciseIdentifier":"s:Sb"}],"abstract":[],"identifier":"doc:\/\/Godot\/documentation\/Godot\/TreeItem\/isChecked(column:)","kind":"symbol","type":"topic","url":"\/documentation\/godot\/treeitem\/ischecked(column:)"},"doc://Godot/documentation/Godot/TreeItem/setButtonDisabled(column:buttonIndex:disabled:)":{"role":"symbol","title":"setButtonDisabled(column:buttonIndex:disabled:)","fragments":[{"kind":"keyword","text":"func"},{"kind":"text","text":" "},{"kind":"identifier","text":"setButtonDisabled"},{"kind":"text","text":"("},{"kind":"externalParam","text":"column"},{"kind":"text","text":": "},{"kind":"typeIdentifier","text":"Int32","preciseIdentifier":"s:s5Int32V"},{"kind":"text","text":", "},{"kind":"externalParam","text":"buttonIndex"},{"kind":"text","text":": "},{"kind":"typeIdentifier","text":"Int32","preciseIdentifier":"s:s5Int32V"},{"kind":"text","text":", "},{"kind":"externalParam","text":"disabled"},{"kind":"text","text":": "},{"kind":"typeIdentifier","text":"Bool","preciseIdentifier":"s:Sb"},{"kind":"text","text":")"}],"abstract":[],"identifier":"doc:\/\/Godot\/documentation\/Godot\/TreeItem\/setButtonDisabled(column:buttonIndex:disabled:)","kind":"symbol","type":"topic","url":"\/documentation\/godot\/treeitem\/setbuttondisabled(column:buttonindex:disabled:)"},"doc://Godot/documentation/Godot/TreeItem/parent()":{"role":"symbol","title":"parent()","fragments":[{"kind":"keyword","text":"func"},{"kind":"text","text":" "},{"kind":"identifier","text":"parent"},{"kind":"text","text":"() -> Godot"},{"kind":"text","text":"."},{"kind":"typeIdentifier","text":"TreeItem","preciseIdentifier":"s:5Godot8TreeItemC"},{"kind":"text","text":"?"}],"abstract":[],"identifier":"doc:\/\/Godot\/documentation\/Godot\/TreeItem\/parent()","kind":"symbol","type":"topic","url":"\/documentation\/godot\/treeitem\/parent()"},"doc://Godot/documentation/Godot/TreeItem/setAutowrapMode(column:autowrapMode:)":{"role":"symbol","title":"setAutowrapMode(column:autowrapMode:)","fragments":[{"kind":"keyword","text":"func"},{"kind":"text","text":" "},{"kind":"identifier","text":"setAutowrapMode"},{"kind":"text","text":"("},{"kind":"externalParam","text":"column"},{"kind":"text","text":": "},{"kind":"typeIdentifier","text":"Int32","preciseIdentifier":"s:s5Int32V"},{"kind":"text","text":", "},{"kind":"externalParam","text":"autowrapMode"},{"kind":"text","text":": Godot"},{"kind":"text","text":"."},{"kind":"typeIdentifier","text":"TextServer","preciseIdentifier":"s:5Godot10TextServerC"},{"kind":"text","text":"."},{"kind":"typeIdentifier","text":"AutowrapMode","preciseIdentifier":"s:5Godot10TextServerC12AutowrapModeO"},{"kind":"text","text":")"}],"abstract":[],"identifier":"doc:\/\/Godot\/documentation\/Godot\/TreeItem\/setAutowrapMode(column:autowrapMode:)","kind":"symbol","type":"topic","url":"\/documentation\/godot\/treeitem\/setautowrapmode(column:autowrapmode:)"},"doc://Godot/documentation/Godot/TreeItem/setExpandRight(column:enable:)":{"role":"symbol","title":"setExpandRight(column:enable:)","fragments":[{"kind":"keyword","text":"func"},{"kind":"text","text":" "},{"kind":"identifier","text":"setExpandRight"},{"kind":"text","text":"("},{"kind":"externalParam","text":"column"},{"kind":"text","text":": "},{"kind":"typeIdentifier","text":"Int32","preciseIdentifier":"s:s5Int32V"},{"kind":"text","text":", "},{"kind":"externalParam","text":"enable"},{"kind":"text","text":": "},{"kind":"typeIdentifier","text":"Bool","preciseIdentifier":"s:Sb"},{"kind":"text","text":")"}],"abstract":[],"identifier":"doc:\/\/Godot\/documentation\/Godot\/TreeItem\/setExpandRight(column:enable:)","kind":"symbol","type":"topic","url":"\/documentation\/godot\/treeitem\/setexpandright(column:enable:)"},"doc://Godot/documentation/Godot/TreeItem/setIconRegion(column:region:)":{"role":"symbol","title":"setIconRegion(column:region:)","fragments":[{"kind":"keyword","text":"func"},{"kind":"text","text":" "},{"kind":"identifier","text":"setIconRegion"},{"kind":"text","text":"("},{"kind":"externalParam","text":"column"},{"kind":"text","text":": "},{"kind":"typeIdentifier","text":"Int32","preciseIdentifier":"s:s5Int32V"},{"kind":"text","text":", "},{"kind":"externalParam","text":"region"},{"kind":"text","text":": Godot"},{"kind":"text","text":"."},{"kind":"typeIdentifier","text":"Rect2","preciseIdentifier":"s:5Godot5Rect2V"},{"kind":"text","text":")"}],"abstract":[],"identifier":"doc:\/\/Godot\/documentation\/Godot\/TreeItem\/setIconRegion(column:region:)","kind":"symbol","type":"topic","url":"\/documentation\/godot\/treeitem\/seticonregion(column:region:)"},"doc://Godot/documentation/Godot/TreeItem/eraseButton(column:buttonIndex:)":{"role":"symbol","title":"eraseButton(column:buttonIndex:)","fragments":[{"kind":"keyword","text":"func"},{"kind":"text","text":" "},{"kind":"identifier","text":"eraseButton"},{"kind":"text","text":"("},{"kind":"externalParam","text":"column"},{"kind":"text","text":": "},{"kind":"typeIdentifier","text":"Int32","preciseIdentifier":"s:s5Int32V"},{"kind":"text","text":", "},{"kind":"externalParam","text":"buttonIndex"},{"kind":"text","text":": "},{"kind":"typeIdentifier","text":"Int32","preciseIdentifier":"s:s5Int32V"},{"kind":"text","text":")"}],"abstract":[],"identifier":"doc:\/\/Godot\/documentation\/Godot\/TreeItem\/eraseButton(column:buttonIndex:)","kind":"symbol","type":"topic","url":"\/documentation\/godot\/treeitem\/erasebutton(column:buttonindex:)"},"doc://Godot/documentation/Godot/TreeItem/iconMaxWidth(column:)":{"role":"symbol","title":"iconMaxWidth(column:)","fragments":[{"kind":"keyword","text":"func"},{"kind":"text","text":" "},{"kind":"identifier","text":"iconMaxWidth"},{"kind":"text","text":"("},{"kind":"externalParam","text":"column"},{"kind":"text","text":": "},{"kind":"typeIdentifier","text":"Int32","preciseIdentifier":"s:s5Int32V"},{"kind":"text","text":") -> "},{"kind":"typeIdentifier","text":"Int32","preciseIdentifier":"s:s5Int32V"}],"abstract":[],"identifier":"doc:\/\/Godot\/documentation\/Godot\/TreeItem\/iconMaxWidth(column:)","kind":"symbol","type":"topic","url":"\/documentation\/godot\/treeitem\/iconmaxwidth(column:)"},"doc://Godot/documentation/Godot/TreeItem/isEditable(column:)":{"role":"symbol","title":"isEditable(column:)","fragments":[{"kind":"keyword","text":"func"},{"kind":"text","text":" "},{"kind":"identifier","text":"isEditable"},{"kind":"text","text":"("},{"kind":"externalParam","text":"column"},{"kind":"text","text":": "},{"kind":"typeIdentifier","text":"Int32","preciseIdentifier":"s:s5Int32V"},{"kind":"text","text":") -> "},{"kind":"typeIdentifier","text":"Bool","preciseIdentifier":"s:Sb"}],"abstract":[],"identifier":"doc:\/\/Godot\/documentation\/Godot\/TreeItem\/isEditable(column:)","kind":"symbol","type":"topic","url":"\/documentation\/godot\/treeitem\/iseditable(column:)"},"doc://Godot/documentation/Godot/VariantConvertible":{"role":"symbol","title":"VariantConvertible","fragments":[{"kind":"keyword","text":"protocol"},{"kind":"text","text":" "},{"kind":"identifier","text":"VariantConvertible"}],"abstract":[{"type":"text","text":"A type that can be converted from, and to, a variant."}],"identifier":"doc:\/\/Godot\/documentation\/Godot\/VariantConvertible","kind":"symbol","type":"topic","navigatorTitle":[{"kind":"identifier","text":"VariantConvertible"}],"url":"\/documentation\/godot\/variantconvertible"},"doc://Godot/documentation/Godot/TreeItem/setRange(column:value:)":{"role":"symbol","title":"setRange(column:value:)","fragments":[{"kind":"keyword","text":"func"},{"kind":"text","text":" "},{"kind":"identifier","text":"setRange"},{"kind":"text","text":"("},{"kind":"externalParam","text":"column"},{"kind":"text","text":": "},{"kind":"typeIdentifier","text":"Int32","preciseIdentifier":"s:s5Int32V"},{"kind":"text","text":", "},{"kind":"externalParam","text":"value"},{"kind":"text","text":": "},{"kind":"typeIdentifier","text":"Double","preciseIdentifier":"s:Sd"},{"kind":"text","text":")"}],"abstract":[],"identifier":"doc:\/\/Godot\/documentation\/Godot\/TreeItem\/setRange(column:value:)","kind":"symbol","type":"topic","url":"\/documentation\/godot\/treeitem\/setrange(column:value:)"},"doc://Godot/documentation/Godot/TreeItem/moveBefore(item:)":{"role":"symbol","title":"moveBefore(item:)","fragments":[{"kind":"keyword","text":"func"},{"kind":"text","text":" "},{"kind":"identifier","text":"moveBefore"},{"kind":"text","text":"("},{"kind":"externalParam","text":"item"},{"kind":"text","text":": Godot"},{"kind":"text","text":"."},{"kind":"typeIdentifier","text":"TreeItem","preciseIdentifier":"s:5Godot8TreeItemC"},{"kind":"text","text":"?)"}],"abstract":[],"identifier":"doc:\/\/Godot\/documentation\/Godot\/TreeItem\/moveBefore(item:)","kind":"symbol","type":"topic","url":"\/documentation\/godot\/treeitem\/movebefore(item:)"},"doc://Godot/documentation/Godot/TreeItem/callRecursive(method:_:)":{"role":"symbol","title":"callRecursive(method:_:)","fragments":[{"kind":"keyword","text":"func"},{"kind":"text","text":" "},{"kind":"identifier","text":"callRecursive"},{"kind":"text","text":"<each "},{"kind":"genericParameter","text":"VariantRest"},{"kind":"text","text":">("},{"kind":"externalParam","text":"method"},{"kind":"text","text":": Godot"},{"kind":"text","text":"."},{"kind":"typeIdentifier","text":"GodotStringName","preciseIdentifier":"s:5Godot0A10StringNameV"},{"kind":"text","text":", "},{"kind":"keyword","text":"repeat"},{"kind":"text","text":" "},{"kind":"keyword","text":"each"},{"kind":"text","text":" "},{"kind":"typeIdentifier","text":"VariantRest","preciseIdentifier":"s:5Godot8TreeItemC13callRecursive6method_yAA0A10StringNameV_xxQptRvzAA20ConvertibleToVariantRzlF0K4RestL_xmfp"},{"kind":"text","text":")"}],"abstract":[],"identifier":"doc:\/\/Godot\/documentation\/Godot\/TreeItem\/callRecursive(method:_:)","kind":"symbol","type":"topic","url":"\/documentation\/godot\/treeitem\/callrecursive(method:_:)"},"doc://Godot/documentation/Godot/TreeItem/autowrapMode(column:)":{"role":"symbol","title":"autowrapMode(column:)","fragments":[{"kind":"keyword","text":"func"},{"kind":"text","text":" "},{"kind":"identifier","text":"autowrapMode"},{"kind":"text","text":"("},{"kind":"externalParam","text":"column"},{"kind":"text","text":": "},{"kind":"typeIdentifier","text":"Int32","preciseIdentifier":"s:s5Int32V"},{"kind":"text","text":") -> Godot"},{"kind":"text","text":"."},{"kind":"typeIdentifier","text":"TextServer","preciseIdentifier":"s:5Godot10TextServerC"},{"kind":"text","text":"."},{"kind":"typeIdentifier","text":"AutowrapMode","preciseIdentifier":"s:5Godot10TextServerC12AutowrapModeO"}],"abstract":[],"identifier":"doc:\/\/Godot\/documentation\/Godot\/TreeItem\/autowrapMode(column:)","kind":"symbol","type":"topic","url":"\/documentation\/godot\/treeitem\/autowrapmode(column:)"},"doc://Godot/documentation/Godot/TreeItem/setText(column:text:)":{"role":"symbol","title":"setText(column:text:)","fragments":[{"kind":"keyword","text":"func"},{"kind":"text","text":" "},{"kind":"identifier","text":"setText"},{"kind":"text","text":"("},{"kind":"externalParam","text":"column"},{"kind":"text","text":": "},{"kind":"typeIdentifier","text":"Int32","preciseIdentifier":"s:s5Int32V"},{"kind":"text","text":", "},{"kind":"externalParam","text":"text"},{"kind":"text","text":": Godot"},{"kind":"text","text":"."},{"kind":"typeIdentifier","text":"GodotString","preciseIdentifier":"s:5Godot0A6StringV"},{"kind":"text","text":")"}],"abstract":[],"identifier":"doc:\/\/Godot\/documentation\/Godot\/TreeItem\/setText(column:text:)","kind":"symbol","type":"topic","url":"\/documentation\/godot\/treeitem\/settext(column:text:)"},"doc://Godot/documentation/Godot/TreeItem/setCollapsedRecursive(enable:)":{"role":"symbol","title":"setCollapsedRecursive(enable:)","fragments":[{"kind":"keyword","text":"func"},{"kind":"text","text":" "},{"kind":"identifier","text":"setCollapsedRecursive"},{"kind":"text","text":"("},{"kind":"externalParam","text":"enable"},{"kind":"text","text":": "},{"kind":"typeIdentifier","text":"Bool","preciseIdentifier":"s:Sb"},{"kind":"text","text":")"}],"abstract":[],"identifier":"doc:\/\/Godot\/documentation\/Godot\/TreeItem\/setCollapsedRecursive(enable:)","kind":"symbol","type":"topic","url":"\/documentation\/godot\/treeitem\/setcollapsedrecursive(enable:)"},"doc://Godot/documentation/Godot/TreeItem/cellMode(column:)":{"role":"symbol","title":"cellMode(column:)","fragments":[{"kind":"keyword","text":"func"},{"kind":"text","text":" "},{"kind":"identifier","text":"cellMode"},{"kind":"text","text":"("},{"kind":"externalParam","text":"column"},{"kind":"text","text":": "},{"kind":"typeIdentifier","text":"Int32","preciseIdentifier":"s:s5Int32V"},{"kind":"text","text":") -> Godot"},{"kind":"text","text":"."},{"kind":"typeIdentifier","text":"TreeItem","preciseIdentifier":"s:5Godot8TreeItemC"},{"kind":"text","text":"."},{"kind":"typeIdentifier","text":"TreeCellMode","preciseIdentifier":"s:5Godot8TreeItemC0B8CellModeO"}],"abstract":[],"identifier":"doc:\/\/Godot\/documentation\/Godot\/TreeItem\/cellMode(column:)","kind":"symbol","type":"topic","url":"\/documentation\/godot\/treeitem\/cellmode(column:)"},"doc://Godot/documentation/Godot/ConvertibleFromVariant":{"role":"symbol","title":"ConvertibleFromVariant","fragments":[{"kind":"keyword","text":"protocol"},{"kind":"text","text":" "},{"kind":"identifier","text":"ConvertibleFromVariant"}],"abstract":[{"type":"text","text":"A type that can be converted from a variant."}],"identifier":"doc:\/\/Godot\/documentation\/Godot\/ConvertibleFromVariant","kind":"symbol","type":"topic","navigatorTitle":[{"kind":"identifier","text":"ConvertibleFromVariant"}],"url":"\/documentation\/godot\/convertiblefromvariant"},"doc://Godot/documentation/Godot":{"images":[{"type":"icon","identifier":"godot-swift_logo.png"}],"role":"collection","title":"Godot","abstract":[{"type":"text","text":"A library for interacting with Godot using Swift code."}],"identifier":"doc:\/\/Godot\/documentation\/Godot","kind":"symbol","type":"topic","url":"\/documentation\/godot"},"doc://Godot/documentation/Godot/TreeItem/setRangeConfig(column:min:max:step:expr:)":{"role":"symbol","title":"setRangeConfig(column:min:max:step:expr:)","fragments":[{"kind":"keyword","text":"func"},{"kind":"text","text":" "},{"kind":"identifier","text":"setRangeConfig"},{"kind":"text","text":"("},{"kind":"externalParam","text":"column"},{"kind":"text","text":": "},{"kind":"typeIdentifier","text":"Int32","preciseIdentifier":"s:s5Int32V"},{"kind":"text","text":", "},{"kind":"externalParam","text":"min"},{"kind":"text","text":": "},{"kind":"typeIdentifier","text":"Double","preciseIdentifier":"s:Sd"},{"kind":"text","text":", "},{"kind":"externalParam","text":"max"},{"kind":"text","text":": "},{"kind":"typeIdentifier","text":"Double","preciseIdentifier":"s:Sd"},{"kind":"text","text":", "},{"kind":"externalParam","text":"step"},{"kind":"text","text":": "},{"kind":"typeIdentifier","text":"Double","preciseIdentifier":"s:Sd"},{"kind":"text","text":", "},{"kind":"externalParam","text":"expr"},{"kind":"text","text":": "},{"kind":"typeIdentifier","text":"Bool","preciseIdentifier":"s:Sb"},{"kind":"text","text":")"}],"abstract":[],"identifier":"doc:\/\/Godot\/documentation\/Godot\/TreeItem\/setRangeConfig(column:min:max:step:expr:)","kind":"symbol","type":"topic","url":"\/documentation\/godot\/treeitem\/setrangeconfig(column:min:max:step:expr:)"},"doc://Godot/documentation/Godot/TreeItem/setIcon(column:texture:)":{"role":"symbol","title":"setIcon(column:texture:)","fragments":[{"kind":"keyword","text":"func"},{"kind":"text","text":" "},{"kind":"identifier","text":"setIcon"},{"kind":"text","text":"("},{"kind":"externalParam","text":"column"},{"kind":"text","text":": "},{"kind":"typeIdentifier","text":"Int32","preciseIdentifier":"s:s5Int32V"},{"kind":"text","text":", "},{"kind":"externalParam","text":"texture"},{"kind":"text","text":": Godot"},{"kind":"text","text":"."},{"kind":"typeIdentifier","text":"Texture2D","preciseIdentifier":"s:5Godot9Texture2DC"},{"kind":"text","text":"?)"}],"abstract":[],"identifier":"doc:\/\/Godot\/documentation\/Godot\/TreeItem\/setIcon(column:texture:)","kind":"symbol","type":"topic","url":"\/documentation\/godot\/treeitem\/seticon(column:texture:)"},"doc://Godot/documentation/Godot/TreeItem/setMetadata(column:meta:)":{"role":"symbol","title":"setMetadata(column:meta:)","fragments":[{"kind":"keyword","text":"func"},{"kind":"text","text":" "},{"kind":"identifier","text":"setMetadata"},{"kind":"text","text":"<"},{"kind":"genericParameter","text":"Variant1"},{"kind":"text","text":">("},{"kind":"externalParam","text":"column"},{"kind":"text","text":": "},{"kind":"typeIdentifier","text":"Int32","preciseIdentifier":"s:s5Int32V"},{"kind":"text","text":", "},{"kind":"externalParam","text":"meta"},{"kind":"text","text":": "},{"kind":"typeIdentifier","text":"Variant1","preciseIdentifier":"s:5Godot8TreeItemC11setMetadata6column4metays5Int32V_xtAA20ConvertibleToVariantRzlF8Variant1L_xmfp"},{"kind":"text","text":")"}],"abstract":[],"identifier":"doc:\/\/Godot\/documentation\/Godot\/TreeItem\/setMetadata(column:meta:)","kind":"symbol","type":"topic","url":"\/documentation\/godot\/treeitem\/setmetadata(column:meta:)"},"doc://Godot/documentation/Godot/TreeItem/expandRight(column:)":{"role":"symbol","title":"expandRight(column:)","fragments":[{"kind":"keyword","text":"func"},{"kind":"text","text":" "},{"kind":"identifier","text":"expandRight"},{"kind":"text","text":"("},{"kind":"externalParam","text":"column"},{"kind":"text","text":": "},{"kind":"typeIdentifier","text":"Int32","preciseIdentifier":"s:s5Int32V"},{"kind":"text","text":") -> "},{"kind":"typeIdentifier","text":"Bool","preciseIdentifier":"s:Sb"}],"abstract":[],"identifier":"doc:\/\/Godot\/documentation\/Godot\/TreeItem\/expandRight(column:)","kind":"symbol","type":"topic","url":"\/documentation\/godot\/treeitem\/expandright(column:)"},"doc://Godot/documentation/Godot/TreeItem/addChild(_:)":{"role":"symbol","title":"addChild(_:)","fragments":[{"kind":"keyword","text":"func"},{"kind":"text","text":" "},{"kind":"identifier","text":"addChild"},{"kind":"text","text":"(Godot"},{"kind":"text","text":"."},{"kind":"typeIdentifier","text":"TreeItem","preciseIdentifier":"s:5Godot8TreeItemC"},{"kind":"text","text":"?)"}],"abstract":[],"identifier":"doc:\/\/Godot\/documentation\/Godot\/TreeItem\/addChild(_:)","kind":"symbol","type":"topic","url":"\/documentation\/godot\/treeitem\/addchild(_:)"},"doc://Godot/documentation/Godot/TreeItem/removeChild(_:)":{"role":"symbol","title":"removeChild(_:)","fragments":[{"kind":"keyword","text":"func"},{"kind":"text","text":" "},{"kind":"identifier","text":"removeChild"},{"kind":"text","text":"(Godot"},{"kind":"text","text":"."},{"kind":"typeIdentifier","text":"TreeItem","preciseIdentifier":"s:5Godot8TreeItemC"},{"kind":"text","text":"?)"}],"abstract":[],"identifier":"doc:\/\/Godot\/documentation\/Godot\/TreeItem\/removeChild(_:)","kind":"symbol","type":"topic","url":"\/documentation\/godot\/treeitem\/removechild(_:)"},"doc://Godot/documentation/Godot/TreeItem/setButtonColor(column:buttonIndex:color:)":{"role":"symbol","title":"setButtonColor(column:buttonIndex:color:)","fragments":[{"kind":"keyword","text":"func"},{"kind":"text","text":" "},{"kind":"identifier","text":"setButtonColor"},{"kind":"text","text":"("},{"kind":"externalParam","text":"column"},{"kind":"text","text":": "},{"kind":"typeIdentifier","text":"Int32","preciseIdentifier":"s:s5Int32V"},{"kind":"text","text":", "},{"kind":"externalParam","text":"buttonIndex"},{"kind":"text","text":": "},{"kind":"typeIdentifier","text":"Int32","preciseIdentifier":"s:s5Int32V"},{"kind":"text","text":", "},{"kind":"externalParam","text":"color"},{"kind":"text","text":": Godot"},{"kind":"text","text":"."},{"kind":"typeIdentifier","text":"Color","preciseIdentifier":"s:5Godot5ColorV"},{"kind":"text","text":")"}],"abstract":[],"identifier":"doc:\/\/Godot\/documentation\/Godot\/TreeItem\/setButtonColor(column:buttonIndex:color:)","kind":"symbol","type":"topic","url":"\/documentation\/godot\/treeitem\/setbuttoncolor(column:buttonindex:color:)"},"doc://Godot/documentation/Godot/TreeItem/setChecked(column:checked:)":{"role":"symbol","title":"setChecked(column:checked:)","fragments":[{"kind":"keyword","text":"func"},{"kind":"text","text":" "},{"kind":"identifier","text":"setChecked"},{"kind":"text","text":"("},{"kind":"externalParam","text":"column"},{"kind":"text","text":": "},{"kind":"typeIdentifier","text":"Int32","preciseIdentifier":"s:s5Int32V"},{"kind":"text","text":", "},{"kind":"externalParam","text":"checked"},{"kind":"text","text":": "},{"kind":"typeIdentifier","text":"Bool","preciseIdentifier":"s:Sb"},{"kind":"text","text":")"}],"abstract":[],"identifier":"doc:\/\/Godot\/documentation\/Godot\/TreeItem\/setChecked(column:checked:)","kind":"symbol","type":"topic","url":"\/documentation\/godot\/treeitem\/setchecked(column:checked:)"},"doc://Godot/documentation/Godot/TreeItem/prevInTree(wrap:)":{"role":"symbol","title":"prevInTree(wrap:)","fragments":[{"kind":"keyword","text":"func"},{"kind":"text","text":" "},{"kind":"identifier","text":"prevInTree"},{"kind":"text","text":"("},{"kind":"externalParam","text":"wrap"},{"kind":"text","text":": "},{"kind":"typeIdentifier","text":"Bool","preciseIdentifier":"s:Sb"},{"kind":"text","text":") -> Godot"},{"kind":"text","text":"."},{"kind":"typeIdentifier","text":"TreeItem","preciseIdentifier":"s:5Godot8TreeItemC"},{"kind":"text","text":"?"}],"abstract":[],"identifier":"doc:\/\/Godot\/documentation\/Godot\/TreeItem\/prevInTree(wrap:)","kind":"symbol","type":"topic","url":"\/documentation\/godot\/treeitem\/previntree(wrap:)"},"doc://Godot/documentation/Godot/TreeItem/language(column:)":{"role":"symbol","title":"language(column:)","fragments":[{"kind":"keyword","text":"func"},{"kind":"text","text":" "},{"kind":"identifier","text":"language"},{"kind":"text","text":"("},{"kind":"externalParam","text":"column"},{"kind":"text","text":": "},{"kind":"typeIdentifier","text":"Int32","preciseIdentifier":"s:s5Int32V"},{"kind":"text","text":") -> Godot"},{"kind":"text","text":"."},{"kind":"typeIdentifier","text":"GodotString","preciseIdentifier":"s:5Godot0A6StringV"}],"abstract":[],"identifier":"doc:\/\/Godot\/documentation\/Godot\/TreeItem\/language(column:)","kind":"symbol","type":"topic","url":"\/documentation\/godot\/treeitem\/language(column:)"},"doc://Godot/documentation/Godot/TreeItem/text(column:)":{"role":"symbol","title":"text(column:)","fragments":[{"kind":"keyword","text":"func"},{"kind":"text","text":" "},{"kind":"identifier","text":"text"},{"kind":"text","text":"("},{"kind":"externalParam","text":"column"},{"kind":"text","text":": "},{"kind":"typeIdentifier","text":"Int32","preciseIdentifier":"s:s5Int32V"},{"kind":"text","text":") -> Godot"},{"kind":"text","text":"."},{"kind":"typeIdentifier","text":"GodotString","preciseIdentifier":"s:5Godot0A6StringV"}],"abstract":[],"identifier":"doc:\/\/Godot\/documentation\/Godot\/TreeItem\/text(column:)","kind":"symbol","type":"topic","url":"\/documentation\/godot\/treeitem\/text(column:)"},"doc://Godot/documentation/Godot/TreeItem/buttonById(column:id:)":{"role":"symbol","title":"buttonById(column:id:)","fragments":[{"kind":"keyword","text":"func"},{"kind":"text","text":" "},{"kind":"identifier","text":"buttonById"},{"kind":"text","text":"("},{"kind":"externalParam","text":"column"},{"kind":"text","text":": "},{"kind":"typeIdentifier","text":"Int32","preciseIdentifier":"s:s5Int32V"},{"kind":"text","text":", "},{"kind":"externalParam","text":"id"},{"kind":"text","text":": "},{"kind":"typeIdentifier","text":"Int32","preciseIdentifier":"s:s5Int32V"},{"kind":"text","text":") -> "},{"kind":"typeIdentifier","text":"Int32","preciseIdentifier":"s:s5Int32V"}],"abstract":[],"identifier":"doc:\/\/Godot\/documentation\/Godot\/TreeItem\/buttonById(column:id:)","kind":"symbol","type":"topic","url":"\/documentation\/godot\/treeitem\/buttonbyid(column:id:)"},"doc://Godot/documentation/Godot/TreeItem/iconRegion(column:)":{"role":"symbol","title":"iconRegion(column:)","fragments":[{"kind":"keyword","text":"func"},{"kind":"text","text":" "},{"kind":"identifier","text":"iconRegion"},{"kind":"text","text":"("},{"kind":"externalParam","text":"column"},{"kind":"text","text":": "},{"kind":"typeIdentifier","text":"Int32","preciseIdentifier":"s:s5Int32V"},{"kind":"text","text":") -> Godot"},{"kind":"text","text":"."},{"kind":"typeIdentifier","text":"Rect2","preciseIdentifier":"s:5Godot5Rect2V"}],"abstract":[],"identifier":"doc:\/\/Godot\/documentation\/Godot\/TreeItem\/iconRegion(column:)","kind":"symbol","type":"topic","url":"\/documentation\/godot\/treeitem\/iconregion(column:)"},"doc://Godot/documentation/Godot/TreeItem/structuredTextBidiOverrideOptions(column:)":{"role":"symbol","title":"structuredTextBidiOverrideOptions(column:)","fragments":[{"kind":"keyword","text":"func"},{"kind":"text","text":" "},{"kind":"identifier","text":"structuredTextBidiOverrideOptions"},{"kind":"text","text":"("},{"kind":"externalParam","text":"column"},{"kind":"text","text":": "},{"kind":"typeIdentifier","text":"Int32","preciseIdentifier":"s:s5Int32V"},{"kind":"text","text":") -> Godot"},{"kind":"text","text":"."},{"kind":"typeIdentifier","text":"GodotArray","preciseIdentifier":"s:5Godot0A5ArrayV"}],"abstract":[],"identifier":"doc:\/\/Godot\/documentation\/Godot\/TreeItem\/structuredTextBidiOverrideOptions(column:)","kind":"symbol","type":"topic","url":"\/documentation\/godot\/treeitem\/structuredtextbidioverrideoptions(column:)"},"doc://Godot/documentation/Godot/Object":{"role":"symbol","title":"Object","fragments":[{"kind":"keyword","text":"class"},{"kind":"text","text":" "},{"kind":"identifier","text":"Object"}],"abstract":[],"identifier":"doc:\/\/Godot\/documentation\/Godot\/Object","kind":"symbol","type":"topic","navigatorTitle":[{"kind":"identifier","text":"Object"}],"url":"\/documentation\/godot\/object"},"doc://Godot/documentation/Godot/TreeItem/tree()":{"role":"symbol","title":"tree()","fragments":[{"kind":"keyword","text":"func"},{"kind":"text","text":" "},{"kind":"identifier","text":"tree"},{"kind":"text","text":"() -> Godot"},{"kind":"text","text":"."},{"kind":"typeIdentifier","text":"Tree","preciseIdentifier":"s:5Godot4TreeC"},{"kind":"text","text":"?"}],"abstract":[],"identifier":"doc:\/\/Godot\/documentation\/Godot\/TreeItem\/tree()","kind":"symbol","type":"topic","url":"\/documentation\/godot\/treeitem\/tree()"},"doc://Godot/documentation/Godot/TreeItem/icon(column:)":{"role":"symbol","title":"icon(column:)","fragments":[{"kind":"keyword","text":"func"},{"kind":"text","text":" "},{"kind":"identifier","text":"icon"},{"kind":"text","text":"("},{"kind":"externalParam","text":"column"},{"kind":"text","text":": "},{"kind":"typeIdentifier","text":"Int32","preciseIdentifier":"s:s5Int32V"},{"kind":"text","text":") -> Godot"},{"kind":"text","text":"."},{"kind":"typeIdentifier","text":"Texture2D","preciseIdentifier":"s:5Godot9Texture2DC"},{"kind":"text","text":"?"}],"abstract":[],"identifier":"doc:\/\/Godot\/documentation\/Godot\/TreeItem\/icon(column:)","kind":"symbol","type":"topic","url":"\/documentation\/godot\/treeitem\/icon(column:)"},"doc://Godot/documentation/Godot/TreeItem/moveAfter(item:)":{"role":"symbol","title":"moveAfter(item:)","fragments":[{"kind":"keyword","text":"func"},{"kind":"text","text":" "},{"kind":"identifier","text":"moveAfter"},{"kind":"text","text":"("},{"kind":"externalParam","text":"item"},{"kind":"text","text":": Godot"},{"kind":"text","text":"."},{"kind":"typeIdentifier","text":"TreeItem","preciseIdentifier":"s:5Godot8TreeItemC"},{"kind":"text","text":"?)"}],"abstract":[],"identifier":"doc:\/\/Godot\/documentation\/Godot\/TreeItem\/moveAfter(item:)","kind":"symbol","type":"topic","url":"\/documentation\/godot\/treeitem\/moveafter(item:)"},"doc://Godot/documentation/Godot/TreeItem/textAlignment(column:)":{"role":"symbol","title":"textAlignment(column:)","fragments":[{"kind":"keyword","text":"func"},{"kind":"text","text":" "},{"kind":"identifier","text":"textAlignment"},{"kind":"text","text":"("},{"kind":"externalParam","text":"column"},{"kind":"text","text":": "},{"kind":"typeIdentifier","text":"Int32","preciseIdentifier":"s:s5Int32V"},{"kind":"text","text":") -> Godot"},{"kind":"text","text":"."},{"kind":"typeIdentifier","text":"HorizontalAlignment","preciseIdentifier":"s:5Godot19HorizontalAlignmentO"}],"abstract":[],"identifier":"doc:\/\/Godot\/documentation\/Godot\/TreeItem\/textAlignment(column:)","kind":"symbol","type":"topic","url":"\/documentation\/godot\/treeitem\/textalignment(column:)"},"doc://Godot/documentation/Godot/TreeItem/setCustomBgColor(column:color:justOutline:)":{"role":"symbol","title":"setCustomBgColor(column:color:justOutline:)","fragments":[{"kind":"keyword","text":"func"},{"kind":"text","text":" "},{"kind":"identifier","text":"setCustomBgColor"},{"kind":"text","text":"("},{"kind":"externalParam","text":"column"},{"kind":"text","text":": "},{"kind":"typeIdentifier","text":"Int32","preciseIdentifier":"s:s5Int32V"},{"kind":"text","text":", "},{"kind":"externalParam","text":"color"},{"kind":"text","text":": Godot"},{"kind":"text","text":"."},{"kind":"typeIdentifier","text":"Color","preciseIdentifier":"s:5Godot5ColorV"},{"kind":"text","text":", "},{"kind":"externalParam","text":"justOutline"},{"kind":"text","text":": "},{"kind":"typeIdentifier","text":"Bool","preciseIdentifier":"s:Sb"},{"kind":"text","text":")"}],"abstract":[],"identifier":"doc:\/\/Godot\/documentation\/Godot\/TreeItem\/setCustomBgColor(column:color:justOutline:)","kind":"symbol","type":"topic","url":"\/documentation\/godot\/treeitem\/setcustombgcolor(column:color:justoutline:)"},"doc://Godot/SQ":{"type":"unresolvable","title":"Swift.Equatable","identifier":"doc:\/\/Godot\/SQ"},"doc://Godot/documentation/Godot/TreeItem/customColor(column:)":{"role":"symbol","title":"customColor(column:)","fragments":[{"kind":"keyword","text":"func"},{"kind":"text","text":" "},{"kind":"identifier","text":"customColor"},{"kind":"text","text":"("},{"kind":"externalParam","text":"column"},{"kind":"text","text":": "},{"kind":"typeIdentifier","text":"Int32","preciseIdentifier":"s:s5Int32V"},{"kind":"text","text":") -> Godot"},{"kind":"text","text":"."},{"kind":"typeIdentifier","text":"Color","preciseIdentifier":"s:5Godot5ColorV"}],"abstract":[],"identifier":"doc:\/\/Godot\/documentation\/Godot\/TreeItem\/customColor(column:)","kind":"symbol","type":"topic","url":"\/documentation\/godot\/treeitem\/customcolor(column:)"},"doc://Godot/documentation/Godot/TreeItem/index()":{"role":"symbol","title":"index()","fragments":[{"kind":"keyword","text":"func"},{"kind":"text","text":" "},{"kind":"identifier","text":"index"},{"kind":"text","text":"() -> "},{"kind":"typeIdentifier","text":"Int32","preciseIdentifier":"s:s5Int32V"}],"abstract":[],"identifier":"doc:\/\/Godot\/documentation\/Godot\/TreeItem\/index()","kind":"symbol","type":"topic","url":"\/documentation\/godot\/treeitem\/index()"},"doc://Godot/documentation/Godot/TreeItem/range(column:)":{"role":"symbol","title":"range(column:)","fragments":[{"kind":"keyword","text":"func"},{"kind":"text","text":" "},{"kind":"identifier","text":"range"},{"kind":"text","text":"("},{"kind":"externalParam","text":"column"},{"kind":"text","text":": "},{"kind":"typeIdentifier","text":"Int32","preciseIdentifier":"s:s5Int32V"},{"kind":"text","text":") -> "},{"kind":"typeIdentifier","text":"Double","preciseIdentifier":"s:Sd"}],"abstract":[],"identifier":"doc:\/\/Godot\/documentation\/Godot\/TreeItem\/range(column:)","kind":"symbol","type":"topic","url":"\/documentation\/godot\/treeitem\/range(column:)"},"doc://Godot/documentation/Godot/TreeItem/child(index:)":{"role":"symbol","title":"child(index:)","fragments":[{"kind":"keyword","text":"func"},{"kind":"text","text":" "},{"kind":"identifier","text":"child"},{"kind":"text","text":"("},{"kind":"externalParam","text":"index"},{"kind":"text","text":": "},{"kind":"typeIdentifier","text":"Int32","preciseIdentifier":"s:s5Int32V"},{"kind":"text","text":") -> Godot"},{"kind":"text","text":"."},{"kind":"typeIdentifier","text":"TreeItem","preciseIdentifier":"s:5Godot8TreeItemC"},{"kind":"text","text":"?"}],"abstract":[],"identifier":"doc:\/\/Godot\/documentation\/Godot\/TreeItem\/child(index:)","kind":"symbol","type":"topic","url":"\/documentation\/godot\/treeitem\/child(index:)"},"doc://Godot/documentation/Godot/TreeItem/setStructuredTextBidiOverride(column:parser:)":{"role":"symbol","title":"setStructuredTextBidiOverride(column:parser:)","fragments":[{"kind":"keyword","text":"func"},{"kind":"text","text":" "},{"kind":"identifier","text":"setStructuredTextBidiOverride"},{"kind":"text","text":"("},{"kind":"externalParam","text":"column"},{"kind":"text","text":": "},{"kind":"typeIdentifier","text":"Int32","preciseIdentifier":"s:s5Int32V"},{"kind":"text","text":", "},{"kind":"externalParam","text":"parser"},{"kind":"text","text":": Godot"},{"kind":"text","text":"."},{"kind":"typeIdentifier","text":"TextServer","preciseIdentifier":"s:5Godot10TextServerC"},{"kind":"text","text":"."},{"kind":"typeIdentifier","text":"StructuredTextParser","preciseIdentifier":"s:5Godot10TextServerC010StructuredB6ParserO"},{"kind":"text","text":")"}],"abstract":[],"identifier":"doc:\/\/Godot\/documentation\/Godot\/TreeItem\/setStructuredTextBidiOverride(column:parser:)","kind":"symbol","type":"topic","url":"\/documentation\/godot\/treeitem\/setstructuredtextbidioverride(column:parser:)"},"doc://Godot/documentation/Godot/TreeItem/createChild(index:)":{"role":"symbol","title":"createChild(index:)","fragments":[{"kind":"keyword","text":"func"},{"kind":"text","text":" "},{"kind":"identifier","text":"createChild"},{"kind":"text","text":"("},{"kind":"externalParam","text":"index"},{"kind":"text","text":": "},{"kind":"typeIdentifier","text":"Int32","preciseIdentifier":"s:s5Int32V"},{"kind":"text","text":") -> Godot"},{"kind":"text","text":"."},{"kind":"typeIdentifier","text":"TreeItem","preciseIdentifier":"s:5Godot8TreeItemC"},{"kind":"text","text":"?"}],"abstract":[],"identifier":"doc:\/\/Godot\/documentation\/Godot\/TreeItem\/createChild(index:)","kind":"symbol","type":"topic","url":"\/documentation\/godot\/treeitem\/createchild(index:)"},"doc://Godot/documentation/Godot/TreeItem/nextVisible(wrap:)":{"role":"symbol","title":"nextVisible(wrap:)","fragments":[{"kind":"keyword","text":"func"},{"kind":"text","text":" "},{"kind":"identifier","text":"nextVisible"},{"kind":"text","text":"("},{"kind":"externalParam","text":"wrap"},{"kind":"text","text":": "},{"kind":"typeIdentifier","text":"Bool","preciseIdentifier":"s:Sb"},{"kind":"text","text":") -> Godot"},{"kind":"text","text":"."},{"kind":"typeIdentifier","text":"TreeItem","preciseIdentifier":"s:5Godot8TreeItemC"},{"kind":"text","text":"?"}],"abstract":[],"identifier":"doc:\/\/Godot\/documentation\/Godot\/TreeItem\/nextVisible(wrap:)","kind":"symbol","type":"topic","url":"\/documentation\/godot\/treeitem\/nextvisible(wrap:)"},"doc://Godot/documentation/Godot/TreeItem/isCollapsed":{"role":"symbol","title":"isCollapsed","fragments":[{"kind":"keyword","text":"var"},{"kind":"text","text":" "},{"kind":"identifier","text":"isCollapsed"},{"kind":"text","text":": "},{"kind":"typeIdentifier","text":"Bool","preciseIdentifier":"s:Sb"}],"abstract":[],"identifier":"doc:\/\/Godot\/documentation\/Godot\/TreeItem\/isCollapsed","kind":"symbol","type":"topic","url":"\/documentation\/godot\/treeitem\/iscollapsed"},"doc://Godot/documentation/Godot/TreeItem/setEditable(column:enabled:)":{"role":"symbol","title":"setEditable(column:enabled:)","fragments":[{"kind":"keyword","text":"func"},{"kind":"text","text":" "},{"kind":"identifier","text":"setEditable"},{"kind":"text","text":"("},{"kind":"externalParam","text":"column"},{"kind":"text","text":": "},{"kind":"typeIdentifier","text":"Int32","preciseIdentifier":"s:s5Int32V"},{"kind":"text","text":", "},{"kind":"externalParam","text":"enabled"},{"kind":"text","text":": "},{"kind":"typeIdentifier","text":"Bool","preciseIdentifier":"s:Sb"},{"kind":"text","text":")"}],"abstract":[],"identifier":"doc:\/\/Godot\/documentation\/Godot\/TreeItem\/setEditable(column:enabled:)","kind":"symbol","type":"topic","url":"\/documentation\/godot\/treeitem\/seteditable(column:enabled:)"},"doc://Godot/documentation/Godot/TreeItem/deselect(column:)":{"role":"symbol","title":"deselect(column:)","fragments":[{"kind":"keyword","text":"func"},{"kind":"text","text":" "},{"kind":"identifier","text":"deselect"},{"kind":"text","text":"("},{"kind":"externalParam","text":"column"},{"kind":"text","text":": "},{"kind":"typeIdentifier","text":"Int32","preciseIdentifier":"s:s5Int32V"},{"kind":"text","text":")"}],"abstract":[],"identifier":"doc:\/\/Godot\/documentation\/Godot\/TreeItem\/deselect(column:)","kind":"symbol","type":"topic","url":"\/documentation\/godot\/treeitem\/deselect(column:)"},"doc://Godot/documentation/Godot/TreeItem/setSuffix(column:text:)":{"role":"symbol","title":"setSuffix(column:text:)","fragments":[{"kind":"keyword","text":"func"},{"kind":"text","text":" "},{"kind":"identifier","text":"setSuffix"},{"kind":"text","text":"("},{"kind":"externalParam","text":"column"},{"kind":"text","text":": "},{"kind":"typeIdentifier","text":"Int32","preciseIdentifier":"s:s5Int32V"},{"kind":"text","text":", "},{"kind":"externalParam","text":"text"},{"kind":"text","text":": Godot"},{"kind":"text","text":"."},{"kind":"typeIdentifier","text":"GodotString","preciseIdentifier":"s:5Godot0A6StringV"},{"kind":"text","text":")"}],"abstract":[],"identifier":"doc:\/\/Godot\/documentation\/Godot\/TreeItem\/setSuffix(column:text:)","kind":"symbol","type":"topic","url":"\/documentation\/godot\/treeitem\/setsuffix(column:text:)"},"doc://Godot/documentation/Godot/TreeItem/setCustomAsButton(column:enable:)":{"role":"symbol","title":"setCustomAsButton(column:enable:)","fragments":[{"kind":"keyword","text":"func"},{"kind":"text","text":" "},{"kind":"identifier","text":"setCustomAsButton"},{"kind":"text","text":"("},{"kind":"externalParam","text":"column"},{"kind":"text","text":": "},{"kind":"typeIdentifier","text":"Int32","preciseIdentifier":"s:s5Int32V"},{"kind":"text","text":", "},{"kind":"externalParam","text":"enable"},{"kind":"text","text":": "},{"kind":"typeIdentifier","text":"Bool","preciseIdentifier":"s:Sb"},{"kind":"text","text":")"}],"abstract":[],"identifier":"doc:\/\/Godot\/documentation\/Godot\/TreeItem\/setCustomAsButton(column:enable:)","kind":"symbol","type":"topic","url":"\/documentation\/godot\/treeitem\/setcustomasbutton(column:enable:)"},"doc://Godot/documentation/Godot/TreeItem/isVisible":{"role":"symbol","title":"isVisible","fragments":[{"kind":"keyword","text":"var"},{"kind":"text","text":" "},{"kind":"identifier","text":"isVisible"},{"kind":"text","text":": "},{"kind":"typeIdentifier","text":"Bool","preciseIdentifier":"s:Sb"}],"abstract":[],"identifier":"doc:\/\/Godot\/documentation\/Godot\/TreeItem\/isVisible","kind":"symbol","type":"topic","url":"\/documentation\/godot\/treeitem\/isvisible"},"doc://Godot/documentation/Godot/TreeItem/customMinimumHeight":{"role":"symbol","title":"customMinimumHeight","fragments":[{"kind":"keyword","text":"var"},{"kind":"text","text":" "},{"kind":"identifier","text":"customMinimumHeight"},{"kind":"text","text":": "},{"kind":"typeIdentifier","text":"Int32","preciseIdentifier":"s:s5Int32V"}],"abstract":[],"identifier":"doc:\/\/Godot\/documentation\/Godot\/TreeItem\/customMinimumHeight","kind":"symbol","type":"topic","url":"\/documentation\/godot\/treeitem\/customminimumheight"},"doc://Godot/documentation/Godot/TreeItem/setCustomDraw(column:object:callback:)":{"role":"symbol","title":"setCustomDraw(column:object:callback:)","fragments":[{"kind":"keyword","text":"func"},{"kind":"text","text":" "},{"kind":"identifier","text":"setCustomDraw"},{"kind":"text","text":"("},{"kind":"externalParam","text":"column"},{"kind":"text","text":": "},{"kind":"typeIdentifier","text":"Int32","preciseIdentifier":"s:s5Int32V"},{"kind":"text","text":", "},{"kind":"externalParam","text":"object"},{"kind":"text","text":": Godot"},{"kind":"text","text":"."},{"kind":"typeIdentifier","text":"Object","preciseIdentifier":"s:5Godot6ObjectC"},{"kind":"text","text":"?, "},{"kind":"externalParam","text":"callback"},{"kind":"text","text":": Godot"},{"kind":"text","text":"."},{"kind":"typeIdentifier","text":"GodotStringName","preciseIdentifier":"s:5Godot0A10StringNameV"},{"kind":"text","text":")"}],"abstract":[],"identifier":"doc:\/\/Godot\/documentation\/Godot\/TreeItem\/setCustomDraw(column:object:callback:)","kind":"symbol","type":"topic","url":"\/documentation\/godot\/treeitem\/setcustomdraw(column:object:callback:)"},"doc://Godot/documentation/Godot/TreeItem/isEditMultiline(column:)":{"role":"symbol","title":"isEditMultiline(column:)","fragments":[{"kind":"keyword","text":"func"},{"kind":"text","text":" "},{"kind":"identifier","text":"isEditMultiline"},{"kind":"text","text":"("},{"kind":"externalParam","text":"column"},{"kind":"text","text":": "},{"kind":"typeIdentifier","text":"Int32","preciseIdentifier":"s:s5Int32V"},{"kind":"text","text":") -> "},{"kind":"typeIdentifier","text":"Bool","preciseIdentifier":"s:Sb"}],"abstract":[],"identifier":"doc:\/\/Godot\/documentation\/Godot\/TreeItem\/isEditMultiline(column:)","kind":"symbol","type":"topic","url":"\/documentation\/godot\/treeitem\/iseditmultiline(column:)"},"doc://Godot/documentation/Godot/TreeItem/iconModulate(column:)":{"role":"symbol","title":"iconModulate(column:)","fragments":[{"kind":"keyword","text":"func"},{"kind":"text","text":" "},{"kind":"identifier","text":"iconModulate"},{"kind":"text","text":"("},{"kind":"externalParam","text":"column"},{"kind":"text","text":": "},{"kind":"typeIdentifier","text":"Int32","preciseIdentifier":"s:s5Int32V"},{"kind":"text","text":") -> Godot"},{"kind":"text","text":"."},{"kind":"typeIdentifier","text":"Color","preciseIdentifier":"s:5Godot5ColorV"}],"abstract":[],"identifier":"doc:\/\/Godot\/documentation\/Godot\/TreeItem\/iconModulate(column:)","kind":"symbol","type":"topic","url":"\/documentation\/godot\/treeitem\/iconmodulate(column:)"},"doc://Godot/documentation/Godot/TreeItem/setTextAlignment(column:textAlignment:)":{"role":"symbol","title":"setTextAlignment(column:textAlignment:)","fragments":[{"kind":"keyword","text":"func"},{"kind":"text","text":" "},{"kind":"identifier","text":"setTextAlignment"},{"kind":"text","text":"("},{"kind":"externalParam","text":"column"},{"kind":"text","text":": "},{"kind":"typeIdentifier","text":"Int32","preciseIdentifier":"s:s5Int32V"},{"kind":"text","text":", "},{"kind":"externalParam","text":"textAlignment"},{"kind":"text","text":": Godot"},{"kind":"text","text":"."},{"kind":"typeIdentifier","text":"HorizontalAlignment","preciseIdentifier":"s:5Godot19HorizontalAlignmentO"},{"kind":"text","text":")"}],"abstract":[],"identifier":"doc:\/\/Godot\/documentation\/Godot\/TreeItem\/setTextAlignment(column:textAlignment:)","kind":"symbol","type":"topic","url":"\/documentation\/godot\/treeitem\/settextalignment(column:textalignment:)"},"doc://Godot/documentation/Godot/TreeItem/rangeConfig(column:)":{"role":"symbol","title":"rangeConfig(column:)","fragments":[{"kind":"keyword","text":"func"},{"kind":"text","text":" "},{"kind":"identifier","text":"rangeConfig"},{"kind":"text","text":"("},{"kind":"externalParam","text":"column"},{"kind":"text","text":": "},{"kind":"typeIdentifier","text":"Int32","preciseIdentifier":"s:s5Int32V"},{"kind":"text","text":") -> Godot"},{"kind":"text","text":"."},{"kind":"typeIdentifier","text":"GodotDictionary","preciseIdentifier":"s:5Godot0A10DictionaryV"}],"abstract":[],"identifier":"doc:\/\/Godot\/documentation\/Godot\/TreeItem\/rangeConfig(column:)","kind":"symbol","type":"topic","url":"\/documentation\/godot\/treeitem\/rangeconfig(column:)"},"doc://Godot/documentation/Godot/TreeItem/uncollapseTree()":{"role":"symbol","title":"uncollapseTree()","fragments":[{"kind":"keyword","text":"func"},{"kind":"text","text":" "},{"kind":"identifier","text":"uncollapseTree"},{"kind":"text","text":"()"}],"abstract":[],"identifier":"doc:\/\/Godot\/documentation\/Godot\/TreeItem\/uncollapseTree()","kind":"symbol","type":"topic","url":"\/documentation\/godot\/treeitem\/uncollapsetree()"},"doc://Godot/documentation/Godot/TreeItem/setIndeterminate(column:indeterminate:)":{"role":"symbol","title":"setIndeterminate(column:indeterminate:)","fragments":[{"kind":"keyword","text":"func"},{"kind":"text","text":" "},{"kind":"identifier","text":"setIndeterminate"},{"kind":"text","text":"("},{"kind":"externalParam","text":"column"},{"kind":"text","text":": "},{"kind":"typeIdentifier","text":"Int32","preciseIdentifier":"s:s5Int32V"},{"kind":"text","text":", "},{"kind":"externalParam","text":"indeterminate"},{"kind":"text","text":": "},{"kind":"typeIdentifier","text":"Bool","preciseIdentifier":"s:Sb"},{"kind":"text","text":")"}],"abstract":[],"identifier":"doc:\/\/Godot\/documentation\/Godot\/TreeItem\/setIndeterminate(column:indeterminate:)","kind":"symbol","type":"topic","url":"\/documentation\/godot\/treeitem\/setindeterminate(column:indeterminate:)"},"doc://Godot/documentation/Godot/TreeItem/propagateCheck(column:emitSignal:)":{"role":"symbol","title":"propagateCheck(column:emitSignal:)","fragments":[{"kind":"keyword","text":"func"},{"kind":"text","text":" "},{"kind":"identifier","text":"propagateCheck"},{"kind":"text","text":"("},{"kind":"externalParam","text":"column"},{"kind":"text","text":": "},{"kind":"typeIdentifier","text":"Int32","preciseIdentifier":"s:s5Int32V"},{"kind":"text","text":", "},{"kind":"externalParam","text":"emitSignal"},{"kind":"text","text":": "},{"kind":"typeIdentifier","text":"Bool","preciseIdentifier":"s:Sb"},{"kind":"text","text":")"}],"abstract":[],"identifier":"doc:\/\/Godot\/documentation\/Godot\/TreeItem\/propagateCheck(column:emitSignal:)","kind":"symbol","type":"topic","url":"\/documentation\/godot\/treeitem\/propagatecheck(column:emitsignal:)"},"doc://Godot/documentation/Godot/TreeItem/setIconMaxWidth(column:width:)":{"role":"symbol","title":"setIconMaxWidth(column:width:)","fragments":[{"kind":"keyword","text":"func"},{"kind":"text","text":" "},{"kind":"identifier","text":"setIconMaxWidth"},{"kind":"text","text":"("},{"kind":"externalParam","text":"column"},{"kind":"text","text":": "},{"kind":"typeIdentifier","text":"Int32","preciseIdentifier":"s:s5Int32V"},{"kind":"text","text":", "},{"kind":"externalParam","text":"width"},{"kind":"text","text":": "},{"kind":"typeIdentifier","text":"Int32","preciseIdentifier":"s:s5Int32V"},{"kind":"text","text":")"}],"abstract":[],"identifier":"doc:\/\/Godot\/documentation\/Godot\/TreeItem\/setIconMaxWidth(column:width:)","kind":"symbol","type":"topic","url":"\/documentation\/godot\/treeitem\/seticonmaxwidth(column:width:)"},"doc://Godot/documentation/Godot/TreeItem/setCellMode(column:mode:)":{"role":"symbol","title":"setCellMode(column:mode:)","fragments":[{"kind":"keyword","text":"func"},{"kind":"text","text":" "},{"kind":"identifier","text":"setCellMode"},{"kind":"text","text":"("},{"kind":"externalParam","text":"column"},{"kind":"text","text":": "},{"kind":"typeIdentifier","text":"Int32","preciseIdentifier":"s:s5Int32V"},{"kind":"text","text":", "},{"kind":"externalParam","text":"mode"},{"kind":"text","text":": Godot"},{"kind":"text","text":"."},{"kind":"typeIdentifier","text":"TreeItem","preciseIdentifier":"s:5Godot8TreeItemC"},{"kind":"text","text":"."},{"kind":"typeIdentifier","text":"TreeCellMode","preciseIdentifier":"s:5Godot8TreeItemC0B8CellModeO"},{"kind":"text","text":")"}],"abstract":[],"identifier":"doc:\/\/Godot\/documentation\/Godot\/TreeItem\/setCellMode(column:mode:)","kind":"symbol","type":"topic","url":"\/documentation\/godot\/treeitem\/setcellmode(column:mode:)"},"doc://Godot/documentation/Godot/TreeItem/customFontSize(column:)":{"role":"symbol","title":"customFontSize(column:)","fragments":[{"kind":"keyword","text":"func"},{"kind":"text","text":" "},{"kind":"identifier","text":"customFontSize"},{"kind":"text","text":"("},{"kind":"externalParam","text":"column"},{"kind":"text","text":": "},{"kind":"typeIdentifier","text":"Int32","preciseIdentifier":"s:s5Int32V"},{"kind":"text","text":") -> "},{"kind":"typeIdentifier","text":"Int32","preciseIdentifier":"s:s5Int32V"}],"abstract":[],"identifier":"doc:\/\/Godot\/documentation\/Godot\/TreeItem\/customFontSize(column:)","kind":"symbol","type":"topic","url":"\/documentation\/godot\/treeitem\/customfontsize(column:)"},"doc://Godot/documentation/Godot/TreeItem/setCustomFont(column:font:)":{"role":"symbol","title":"setCustomFont(column:font:)","fragments":[{"kind":"keyword","text":"func"},{"kind":"text","text":" "},{"kind":"identifier","text":"setCustomFont"},{"kind":"text","text":"("},{"kind":"externalParam","text":"column"},{"kind":"text","text":": "},{"kind":"typeIdentifier","text":"Int32","preciseIdentifier":"s:s5Int32V"},{"kind":"text","text":", "},{"kind":"externalParam","text":"font"},{"kind":"text","text":": Godot"},{"kind":"text","text":"."},{"kind":"typeIdentifier","text":"Font","preciseIdentifier":"s:5Godot4FontC"},{"kind":"text","text":"?)"}],"abstract":[],"identifier":"doc:\/\/Godot\/documentation\/Godot\/TreeItem\/setCustomFont(column:font:)","kind":"symbol","type":"topic","url":"\/documentation\/godot\/treeitem\/setcustomfont(column:font:)"},"doc://Godot/documentation/Godot/TreeItem/select(column:)":{"role":"symbol","title":"select(column:)","fragments":[{"kind":"keyword","text":"func"},{"kind":"text","text":" "},{"kind":"identifier","text":"select"},{"kind":"text","text":"("},{"kind":"externalParam","text":"column"},{"kind":"text","text":": "},{"kind":"typeIdentifier","text":"Int32","preciseIdentifier":"s:s5Int32V"},{"kind":"text","text":")"}],"abstract":[],"identifier":"doc:\/\/Godot\/documentation\/Godot\/TreeItem\/select(column:)","kind":"symbol","type":"topic","url":"\/documentation\/godot\/treeitem\/select(column:)"},"doc://Godot/documentation/Godot/TreeItem/isIndeterminate(column:)":{"role":"symbol","title":"isIndeterminate(column:)","fragments":[{"kind":"keyword","text":"func"},{"kind":"text","text":" "},{"kind":"identifier","text":"isIndeterminate"},{"kind":"text","text":"("},{"kind":"externalParam","text":"column"},{"kind":"text","text":": "},{"kind":"typeIdentifier","text":"Int32","preciseIdentifier":"s:s5Int32V"},{"kind":"text","text":") -> "},{"kind":"typeIdentifier","text":"Bool","preciseIdentifier":"s:Sb"}],"abstract":[],"identifier":"doc:\/\/Godot\/documentation\/Godot\/TreeItem\/isIndeterminate(column:)","kind":"symbol","type":"topic","url":"\/documentation\/godot\/treeitem\/isindeterminate(column:)"},"doc://Godot/documentation/Godot/TreeItem/isSelected(column:)":{"role":"symbol","title":"isSelected(column:)","fragments":[{"kind":"keyword","text":"func"},{"kind":"text","text":" "},{"kind":"identifier","text":"isSelected"},{"kind":"text","text":"("},{"kind":"externalParam","text":"column"},{"kind":"text","text":": "},{"kind":"typeIdentifier","text":"Int32","preciseIdentifier":"s:s5Int32V"},{"kind":"text","text":") -> "},{"kind":"typeIdentifier","text":"Bool","preciseIdentifier":"s:Sb"}],"abstract":[],"identifier":"doc:\/\/Godot\/documentation\/Godot\/TreeItem\/isSelected(column:)","kind":"symbol","type":"topic","url":"\/documentation\/godot\/treeitem\/isselected(column:)"},"doc://Godot/documentation/Godot/TreeItem/setEditMultiline(column:multiline:)":{"role":"symbol","title":"setEditMultiline(column:multiline:)","fragments":[{"kind":"keyword","text":"func"},{"kind":"text","text":" "},{"kind":"identifier","text":"setEditMultiline"},{"kind":"text","text":"("},{"kind":"externalParam","text":"column"},{"kind":"text","text":": "},{"kind":"typeIdentifier","text":"Int32","preciseIdentifier":"s:s5Int32V"},{"kind":"text","text":", "},{"kind":"externalParam","text":"multiline"},{"kind":"text","text":": "},{"kind":"typeIdentifier","text":"Bool","preciseIdentifier":"s:Sb"},{"kind":"text","text":")"}],"abstract":[],"identifier":"doc:\/\/Godot\/documentation\/Godot\/TreeItem\/setEditMultiline(column:multiline:)","kind":"symbol","type":"topic","url":"\/documentation\/godot\/treeitem\/seteditmultiline(column:multiline:)"},"doc://Godot/documentation/Godot/TreeItem/setLanguage(column:language:)":{"role":"symbol","title":"setLanguage(column:language:)","fragments":[{"kind":"keyword","text":"func"},{"kind":"text","text":" "},{"kind":"identifier","text":"setLanguage"},{"kind":"text","text":"("},{"kind":"externalParam","text":"column"},{"kind":"text","text":": "},{"kind":"typeIdentifier","text":"Int32","preciseIdentifier":"s:s5Int32V"},{"kind":"text","text":", "},{"kind":"externalParam","text":"language"},{"kind":"text","text":": Godot"},{"kind":"text","text":"."},{"kind":"typeIdentifier","text":"GodotString","preciseIdentifier":"s:5Godot0A6StringV"},{"kind":"text","text":")"}],"abstract":[],"identifier":"doc:\/\/Godot\/documentation\/Godot\/TreeItem\/setLanguage(column:language:)","kind":"symbol","type":"topic","url":"\/documentation\/godot\/treeitem\/setlanguage(column:language:)"},"doc://Godot/documentation/Godot/TreeItem/prevVisible(wrap:)":{"role":"symbol","title":"prevVisible(wrap:)","fragments":[{"kind":"keyword","text":"func"},{"kind":"text","text":" "},{"kind":"identifier","text":"prevVisible"},{"kind":"text","text":"("},{"kind":"externalParam","text":"wrap"},{"kind":"text","text":": "},{"kind":"typeIdentifier","text":"Bool","preciseIdentifier":"s:Sb"},{"kind":"text","text":") -> Godot"},{"kind":"text","text":"."},{"kind":"typeIdentifier","text":"TreeItem","preciseIdentifier":"s:5Godot8TreeItemC"},{"kind":"text","text":"?"}],"abstract":[],"identifier":"doc:\/\/Godot\/documentation\/Godot\/TreeItem\/prevVisible(wrap:)","kind":"symbol","type":"topic","url":"\/documentation\/godot\/treeitem\/prevvisible(wrap:)"},"doc://Godot/documentation/Godot/TreeItem/button(column:buttonIndex:)":{"role":"symbol","title":"button(column:buttonIndex:)","fragments":[{"kind":"keyword","text":"func"},{"kind":"text","text":" "},{"kind":"identifier","text":"button"},{"kind":"text","text":"("},{"kind":"externalParam","text":"column"},{"kind":"text","text":": "},{"kind":"typeIdentifier","text":"Int32","preciseIdentifier":"s:s5Int32V"},{"kind":"text","text":", "},{"kind":"externalParam","text":"buttonIndex"},{"kind":"text","text":": "},{"kind":"typeIdentifier","text":"Int32","preciseIdentifier":"s:s5Int32V"},{"kind":"text","text":") -> Godot"},{"kind":"text","text":"."},{"kind":"typeIdentifier","text":"Texture2D","preciseIdentifier":"s:5Godot9Texture2DC"},{"kind":"text","text":"?"}],"abstract":[],"identifier":"doc:\/\/Godot\/documentation\/Godot\/TreeItem\/button(column:buttonIndex:)","kind":"symbol","type":"topic","url":"\/documentation\/godot\/treeitem\/button(column:buttonindex:)"},"godot-swift_logo.png":{"alt":"A technology icon representing Godot Swift","type":"image","identifier":"godot-swift_logo.png","variants":[{"url":"\/images\/godot-swift_logo@2x.png","traits":["2x","light"]}]},"doc://Godot/documentation/Godot/TreeItem/buttonTooltipText(column:buttonIndex:)":{"role":"symbol","title":"buttonTooltipText(column:buttonIndex:)","fragments":[{"kind":"keyword","text":"func"},{"kind":"text","text":" "},{"kind":"identifier","text":"buttonTooltipText"},{"kind":"text","text":"("},{"kind":"externalParam","text":"column"},{"kind":"text","text":": "},{"kind":"typeIdentifier","text":"Int32","preciseIdentifier":"s:s5Int32V"},{"kind":"text","text":", "},{"kind":"externalParam","text":"buttonIndex"},{"kind":"text","text":": "},{"kind":"typeIdentifier","text":"Int32","preciseIdentifier":"s:s5Int32V"},{"kind":"text","text":") -> Godot"},{"kind":"text","text":"."},{"kind":"typeIdentifier","text":"GodotString","preciseIdentifier":"s:5Godot0A6StringV"}],"abstract":[],"identifier":"doc:\/\/Godot\/documentation\/Godot\/TreeItem\/buttonTooltipText(column:buttonIndex:)","kind":"symbol","type":"topic","url":"\/documentation\/godot\/treeitem\/buttontooltiptext(column:buttonindex:)"},"doc://Godot/documentation/Godot/TreeItem/textDirection(column:)":{"role":"symbol","title":"textDirection(column:)","fragments":[{"kind":"keyword","text":"func"},{"kind":"text","text":" "},{"kind":"identifier","text":"textDirection"},{"kind":"text","text":"("},{"kind":"externalParam","text":"column"},{"kind":"text","text":": "},{"kind":"typeIdentifier","text":"Int32","preciseIdentifier":"s:s5Int32V"},{"kind":"text","text":") -> Godot"},{"kind":"text","text":"."},{"kind":"typeIdentifier","text":"Control","preciseIdentifier":"s:5Godot7ControlC"},{"kind":"text","text":"."},{"kind":"typeIdentifier","text":"TextDirection","preciseIdentifier":"s:5Godot7ControlC13TextDirectionO"}],"abstract":[],"identifier":"doc:\/\/Godot\/documentation\/Godot\/TreeItem\/textDirection(column:)","kind":"symbol","type":"topic","url":"\/documentation\/godot\/treeitem\/textdirection(column:)"},"doc://Godot/documentation/Godot/TreeItem/callRecursive(method:)":{"role":"symbol","title":"callRecursive(method:)","fragments":[{"kind":"keyword","text":"func"},{"kind":"text","text":" "},{"kind":"identifier","text":"callRecursive"},{"kind":"text","text":"("},{"kind":"externalParam","text":"method"},{"kind":"text","text":": Godot"},{"kind":"text","text":"."},{"kind":"typeIdentifier","text":"GodotStringName","preciseIdentifier":"s:5Godot0A10StringNameV"},{"kind":"text","text":")"}],"abstract":[],"identifier":"doc:\/\/Godot\/documentation\/Godot\/TreeItem\/callRecursive(method:)","kind":"symbol","type":"topic","url":"\/documentation\/godot\/treeitem\/callrecursive(method:)"},"doc://Godot/documentation/Godot/TreeItem/isSelectable(column:)":{"role":"symbol","title":"isSelectable(column:)","fragments":[{"kind":"keyword","text":"func"},{"kind":"text","text":" "},{"kind":"identifier","text":"isSelectable"},{"kind":"text","text":"("},{"kind":"externalParam","text":"column"},{"kind":"text","text":": "},{"kind":"typeIdentifier","text":"Int32","preciseIdentifier":"s:s5Int32V"},{"kind":"text","text":") -> "},{"kind":"typeIdentifier","text":"Bool","preciseIdentifier":"s:Sb"}],"abstract":[],"identifier":"doc:\/\/Godot\/documentation\/Godot\/TreeItem\/isSelectable(column:)","kind":"symbol","type":"topic","url":"\/documentation\/godot\/treeitem\/isselectable(column:)"},"doc://Godot/documentation/Godot/TreeItem/buttonId(column:buttonIndex:)":{"role":"symbol","title":"buttonId(column:buttonIndex:)","fragments":[{"kind":"keyword","text":"func"},{"kind":"text","text":" "},{"kind":"identifier","text":"buttonId"},{"kind":"text","text":"("},{"kind":"externalParam","text":"column"},{"kind":"text","text":": "},{"kind":"typeIdentifier","text":"Int32","preciseIdentifier":"s:s5Int32V"},{"kind":"text","text":", "},{"kind":"externalParam","text":"buttonIndex"},{"kind":"text","text":": "},{"kind":"typeIdentifier","text":"Int32","preciseIdentifier":"s:s5Int32V"},{"kind":"text","text":") -> "},{"kind":"typeIdentifier","text":"Int32","preciseIdentifier":"s:s5Int32V"}],"abstract":[],"identifier":"doc:\/\/Godot\/documentation\/Godot\/TreeItem\/buttonId(column:buttonIndex:)","kind":"symbol","type":"topic","url":"\/documentation\/godot\/treeitem\/buttonid(column:buttonindex:)"},"doc://Godot/documentation/Godot/TreeItem/setStructuredTextBidiOverrideOptions(column:args:)":{"role":"symbol","title":"setStructuredTextBidiOverrideOptions(column:args:)","fragments":[{"kind":"keyword","text":"func"},{"kind":"text","text":" "},{"kind":"identifier","text":"setStructuredTextBidiOverrideOptions"},{"kind":"text","text":"("},{"kind":"externalParam","text":"column"},{"kind":"text","text":": "},{"kind":"typeIdentifier","text":"Int32","preciseIdentifier":"s:s5Int32V"},{"kind":"text","text":", "},{"kind":"externalParam","text":"args"},{"kind":"text","text":": Godot"},{"kind":"text","text":"."},{"kind":"typeIdentifier","text":"GodotArray","preciseIdentifier":"s:5Godot0A5ArrayV"},{"kind":"text","text":")"}],"abstract":[],"identifier":"doc:\/\/Godot\/documentation\/Godot\/TreeItem\/setStructuredTextBidiOverrideOptions(column:args:)","kind":"symbol","type":"topic","url":"\/documentation\/godot\/treeitem\/setstructuredtextbidioverrideoptions(column:args:)"},"doc://Godot/documentation/Godot/TreeItem/suffix(column:)":{"role":"symbol","title":"suffix(column:)","fragments":[{"kind":"keyword","text":"func"},{"kind":"text","text":" "},{"kind":"identifier","text":"suffix"},{"kind":"text","text":"("},{"kind":"externalParam","text":"column"},{"kind":"text","text":": "},{"kind":"typeIdentifier","text":"Int32","preciseIdentifier":"s:s5Int32V"},{"kind":"text","text":") -> Godot"},{"kind":"text","text":"."},{"kind":"typeIdentifier","text":"GodotString","preciseIdentifier":"s:5Godot0A6StringV"}],"abstract":[],"identifier":"doc:\/\/Godot\/documentation\/Godot\/TreeItem\/suffix(column:)","kind":"symbol","type":"topic","url":"\/documentation\/godot\/treeitem\/suffix(column:)"},"doc://Godot/documentation/Godot/TreeItem/isButtonDisabled(column:buttonIndex:)":{"role":"symbol","title":"isButtonDisabled(column:buttonIndex:)","fragments":[{"kind":"keyword","text":"func"},{"kind":"text","text":" "},{"kind":"identifier","text":"isButtonDisabled"},{"kind":"text","text":"("},{"kind":"externalParam","text":"column"},{"kind":"text","text":": "},{"kind":"typeIdentifier","text":"Int32","preciseIdentifier":"s:s5Int32V"},{"kind":"text","text":", "},{"kind":"externalParam","text":"buttonIndex"},{"kind":"text","text":": "},{"kind":"typeIdentifier","text":"Int32","preciseIdentifier":"s:s5Int32V"},{"kind":"text","text":") -> "},{"kind":"typeIdentifier","text":"Bool","preciseIdentifier":"s:Sb"}],"abstract":[],"identifier":"doc:\/\/Godot\/documentation\/Godot\/TreeItem\/isButtonDisabled(column:buttonIndex:)","kind":"symbol","type":"topic","url":"\/documentation\/godot\/treeitem\/isbuttondisabled(column:buttonindex:)"},"doc://Godot/documentation/Godot/TreeItem/structuredTextBidiOverride(column:)":{"role":"symbol","title":"structuredTextBidiOverride(column:)","fragments":[{"kind":"keyword","text":"func"},{"kind":"text","text":" "},{"kind":"identifier","text":"structuredTextBidiOverride"},{"kind":"text","text":"("},{"kind":"externalParam","text":"column"},{"kind":"text","text":": "},{"kind":"typeIdentifier","text":"Int32","preciseIdentifier":"s:s5Int32V"},{"kind":"text","text":") -> Godot"},{"kind":"text","text":"."},{"kind":"typeIdentifier","text":"TextServer","preciseIdentifier":"s:5Godot10TextServerC"},{"kind":"text","text":"."},{"kind":"typeIdentifier","text":"StructuredTextParser","preciseIdentifier":"s:5Godot10TextServerC010StructuredB6ParserO"}],"abstract":[],"identifier":"doc:\/\/Godot\/documentation\/Godot\/TreeItem\/structuredTextBidiOverride(column:)","kind":"symbol","type":"topic","url":"\/documentation\/godot\/treeitem\/structuredtextbidioverride(column:)"},"doc://Godot/documentation/Godot/TreeItem/next()":{"role":"symbol","title":"next()","fragments":[{"kind":"keyword","text":"func"},{"kind":"text","text":" "},{"kind":"identifier","text":"next"},{"kind":"text","text":"() -> Godot"},{"kind":"text","text":"."},{"kind":"typeIdentifier","text":"TreeItem","preciseIdentifier":"s:5Godot8TreeItemC"},{"kind":"text","text":"?"}],"abstract":[],"identifier":"doc:\/\/Godot\/documentation\/Godot\/TreeItem\/next()","kind":"symbol","type":"topic","url":"\/documentation\/godot\/treeitem\/next()"},"doc://Godot/documentation/Godot/TreeItem/setButton(column:buttonIndex:button:)":{"role":"symbol","title":"setButton(column:buttonIndex:button:)","fragments":[{"kind":"keyword","text":"func"},{"kind":"text","text":" "},{"kind":"identifier","text":"setButton"},{"kind":"text","text":"("},{"kind":"externalParam","text":"column"},{"kind":"text","text":": "},{"kind":"typeIdentifier","text":"Int32","preciseIdentifier":"s:s5Int32V"},{"kind":"text","text":", "},{"kind":"externalParam","text":"buttonIndex"},{"kind":"text","text":": "},{"kind":"typeIdentifier","text":"Int32","preciseIdentifier":"s:s5Int32V"},{"kind":"text","text":", "},{"kind":"externalParam","text":"button"},{"kind":"text","text":": Godot"},{"kind":"text","text":"."},{"kind":"typeIdentifier","text":"Texture2D","preciseIdentifier":"s:5Godot9Texture2DC"},{"kind":"text","text":"?)"}],"abstract":[],"identifier":"doc:\/\/Godot\/documentation\/Godot\/TreeItem\/setButton(column:buttonIndex:button:)","kind":"symbol","type":"topic","url":"\/documentation\/godot\/treeitem\/setbutton(column:buttonindex:button:)"},"doc://Godot/documentation/Godot/TreeItem/buttonCount(column:)":{"role":"symbol","title":"buttonCount(column:)","fragments":[{"kind":"keyword","text":"func"},{"kind":"text","text":" "},{"kind":"identifier","text":"buttonCount"},{"kind":"text","text":"("},{"kind":"externalParam","text":"column"},{"kind":"text","text":": "},{"kind":"typeIdentifier","text":"Int32","preciseIdentifier":"s:s5Int32V"},{"kind":"text","text":") -> "},{"kind":"typeIdentifier","text":"Int32","preciseIdentifier":"s:s5Int32V"}],"abstract":[],"identifier":"doc:\/\/Godot\/documentation\/Godot\/TreeItem\/buttonCount(column:)","kind":"symbol","type":"topic","url":"\/documentation\/godot\/treeitem\/buttoncount(column:)"},"doc://Godot/documentation/Godot/TreeItem/isAnyCollapsed(onlyVisible:)":{"role":"symbol","title":"isAnyCollapsed(onlyVisible:)","fragments":[{"kind":"keyword","text":"func"},{"kind":"text","text":" "},{"kind":"identifier","text":"isAnyCollapsed"},{"kind":"text","text":"("},{"kind":"externalParam","text":"onlyVisible"},{"kind":"text","text":": "},{"kind":"typeIdentifier","text":"Bool","preciseIdentifier":"s:Sb"},{"kind":"text","text":") -> "},{"kind":"typeIdentifier","text":"Bool","preciseIdentifier":"s:Sb"}],"abstract":[],"identifier":"doc:\/\/Godot\/documentation\/Godot\/TreeItem\/isAnyCollapsed(onlyVisible:)","kind":"symbol","type":"topic","url":"\/documentation\/godot\/treeitem\/isanycollapsed(onlyvisible:)"},"doc://Godot/documentation/Godot/TreeItem/tooltipText(column:)":{"role":"symbol","title":"tooltipText(column:)","fragments":[{"kind":"keyword","text":"func"},{"kind":"text","text":" "},{"kind":"identifier","text":"tooltipText"},{"kind":"text","text":"("},{"kind":"externalParam","text":"column"},{"kind":"text","text":": "},{"kind":"typeIdentifier","text":"Int32","preciseIdentifier":"s:s5Int32V"},{"kind":"text","text":") -> Godot"},{"kind":"text","text":"."},{"kind":"typeIdentifier","text":"GodotString","preciseIdentifier":"s:5Godot0A6StringV"}],"abstract":[],"identifier":"doc:\/\/Godot\/documentation\/Godot\/TreeItem\/tooltipText(column:)","kind":"symbol","type":"topic","url":"\/documentation\/godot\/treeitem\/tooltiptext(column:)"},"doc://Godot/documentation/Godot/TreeItem/firstChild()":{"role":"symbol","title":"firstChild()","fragments":[{"kind":"keyword","text":"func"},{"kind":"text","text":" "},{"kind":"identifier","text":"firstChild"},{"kind":"text","text":"() -> Godot"},{"kind":"text","text":"."},{"kind":"typeIdentifier","text":"TreeItem","preciseIdentifier":"s:5Godot8TreeItemC"},{"kind":"text","text":"?"}],"abstract":[],"identifier":"doc:\/\/Godot\/documentation\/Godot\/TreeItem\/firstChild()","kind":"symbol","type":"topic","url":"\/documentation\/godot\/treeitem\/firstchild()"},"doc://Godot/documentation/Godot/TreeItem/setTextDirection(column:direction:)":{"role":"symbol","title":"setTextDirection(column:direction:)","fragments":[{"kind":"keyword","text":"func"},{"kind":"text","text":" "},{"kind":"identifier","text":"setTextDirection"},{"kind":"text","text":"("},{"kind":"externalParam","text":"column"},{"kind":"text","text":": "},{"kind":"typeIdentifier","text":"Int32","preciseIdentifier":"s:s5Int32V"},{"kind":"text","text":", "},{"kind":"externalParam","text":"direction"},{"kind":"text","text":": Godot"},{"kind":"text","text":"."},{"kind":"typeIdentifier","text":"Control","preciseIdentifier":"s:5Godot7ControlC"},{"kind":"text","text":"."},{"kind":"typeIdentifier","text":"TextDirection","preciseIdentifier":"s:5Godot7ControlC13TextDirectionO"},{"kind":"text","text":")"}],"abstract":[],"identifier":"doc:\/\/Godot\/documentation\/Godot\/TreeItem\/setTextDirection(column:direction:)","kind":"symbol","type":"topic","url":"\/documentation\/godot\/treeitem\/settextdirection(column:direction:)"},"doc://Godot/documentation/Godot/TreeItem":{"role":"symbol","title":"TreeItem","fragments":[{"kind":"keyword","text":"class"},{"kind":"text","text":" "},{"kind":"identifier","text":"TreeItem"}],"abstract":[],"identifier":"doc:\/\/Godot\/documentation\/Godot\/TreeItem","kind":"symbol","type":"topic","navigatorTitle":[{"kind":"identifier","text":"TreeItem"}],"url":"\/documentation\/godot\/treeitem"}}}